Workbook

Sheet Start Here
A1: Routing Table, version 3
A2: Built 20 September 2026 for Distill. The spreadsheet is the source of truth; a browsable copy is published as an artifact.
A4: What this file is, in one paragraph
A5: When someone finishes telling the app what they take, buy and do, every item gets looked up here. The row says what kind of thing it is, whether a ring or watch can see its effect, how big that effect is likely to be, what the studies found, and the exact sentence the person should read about it on day one. This table is the product's brain and its voice at the same time.
A6: You never ask the person which tier something is in. The tier comes out of this table plus their own answers (how much they take, what for, where the idea came from). The order the app checks things in is written out below.
A7: Nothing in here diagnoses, treats or prevents anything. Every sentence is about a habit, a dose, or a study. Never about a condition.
A9: What changed in version 4
A10: The table routes on answers, not just names | B10: Five new columns per row. 'Follow-up question' says which question fires for the item (dose and form, frequency, clock time, nights a week, last used, still paying, or an automatic overlap check). 'Rule that flips the tier' is the exact threshold, written as a rule the engine can run: for magnesium, 'form = oxide or spray → form not absorbed; dose under 200 mg elemental → dose too low'. Magnesium glycinate at 400 mg and magnesium oxide at 100 mg are now the same row with two different outcomes, which is the whole point. Rows that need no question say 'none' and route as before.
A11: Why this is load-bearing | B11: The day-one drops screen is generated from Tier 2, and Tier 2 is generated almost entirely from these answers. Without the follow-up questions, almost nothing lands in Tier 2 and that screen is empty. With them, a typical stack produces several drops on day one. See the Worked Example sheet.
A12: Two new reasons for a day-one drop | B12: 'Not being used' (a device in a drawer, a membership with banked credits, an app still billing) and 'overlaps with something else' (two gym memberships, a studio that duplicates a plunge at home, a toner doing the serum's job, collagen gummies next to collagen powder). Both use the same logic as the supplement drops: no test needed, drop it now. The dollar amounts are much larger, because services cost more than powders.
A13: The target person changed, and the table followed | B13: The person with thirty bottles was the old target. The new one is the premium-gym member who spends on services, classes, treatments and skincare, and wants to look and feel good. That person might own two supplements, so the 'cut at least five things in 60 days' promise can't be kept from dose failures alone. Thirty-four new rows cover memberships, class packs, recovery studios, massage memberships, meal services, apps, and a skincare section, plus 19 overlap groups (Overlap Groups sheet).
A14: Skincare is a category now | B14: Sunscreen and retinoids get a 'keep' with the strongest evidence in the file. Toners, second hyaluronic serums, most eye creams, doubled exfoliants and oxidised vitamin C serums are day-one drops. Every skincare verdict is about a product, never about a person's skin.
A15: Magnesium merged | B15: The separate oxide row is gone; the form is now an answer to the magnesium question. Threonate and the spray stay separate because they're different products with different claims.
A17: What changed in version 3
A18: Expected effect size | B18: Every row a wearable can see now has a number: how big the effect is likely to be, in units of one person's normal night-to-night swing. Below 0.8, a two-week test would usually come back inconclusive, so those rows get the honest Tier 3 treatment instead of a test that's set up to fail. The table used to send 81 rows to Tier 1; after the gate it's a much shorter list, and almost all of it is timing and behaviour, not supplements. That is a real finding about the product: the testable core is what people do, not what they swallow.
A19: Run it anyway | B19: Gated rows still let the person choose to run the test, told up front what to expect. Their choice is the point of the product; we just stop pretending a small effect is likely to show.
A20: Read from history | B20: A new column says whether the app can learn about an item from the person's existing wearable data before any test: workouts and wake times are recorded automatically; alcohol, caffeine and supplements only if they've been tagging them in Oura or WHOOP; and alcohol nights have a recognisable pattern (HRV down, resting heart rate up, temperature up, all together) that the app can flag for them to confirm. This is how the day-one 'hypotheses' get made, and it's why the morning-after-drinks screen logs the night rather than assigning it.
A21: Observe only | B21: Some items must never be assigned as an 'on' day: alcohol, nicotine, cannabis, energy drinks, fat burners. The app only records those when they happen, and may assign 'off' days. We never tell anyone to drink.
A22: Fact-check flags | B22: Every Tier 2 row, and every row with a specific number in it, now carries a note saying exactly what to check and where to look. That's 90-odd rows, up from 2. Tier 2 rows tell someone to stop paying for something, so they are the exposure.
A23: Fixes | B23: Two double-parenthesis typos. The sauna habit row no longer carries the membership's cost. A stable key column for the engine. Cost per year as a live formula. A goal-to-number map so the routing has a defined metric for every goal.
A25: The four tiers, in plain words
A26: Tier 1: Tested on you | B26: A wearable can see it, it acts within hours, and the likely effect is big enough to show in two weeks. Three days on, three off, repeat. One number chosen before the start. One word at the end: kept, dropped, or inconclusive, always with the actual number.
A27: Tier 2: No test needed | B27: The answer is already known on day one. Five reasons: the dose is too low, the form isn't absorbed, it's been tested properly and found to do nothing, there's no known way it could work, or it duplicates something they already have. The person sees the money back immediately.
A28: Tier 3: Can't measure it | B28: Either a wearable is blind to it, or the likely effect is too small to see in two weeks. We say which. We show the cost per year and what the studies found, and offer a one-tap daily rating for things you'd feel rather than measure. Tier 3 is NOT 'drop': creatine, fibre, strength training and a personal trainer are Tier 3 and get a 'keep'.
A29: Protected | B29: Anything from a doctor, a blood test, a prescription, a hormone, or tied to a diagnosed condition. Never rated, tested, or suggested for dropping. In the count only if they want it there.
A31: The order the app checks things (top to bottom, first match wins)
A32: 1. Protected? | B32: Doctor or blood test source, prescription, hormone, clinical service, or a diagnosed condition named for it. Stop.
A33: 2. Safety note? | B33: Attach it. A few redirect to Protected (mouth tape with possible sleep apnoea; 5-HTP with an antidepressant).
A34: 3. Goal known? | B34: 'General health' or 'nothing specific' goes to Tier 3 as untestable, cost shown.
A35: 4. Settled without a test? | B35: Run the row's follow-up question. Dose below the floor, form not absorbed, evidence grade N for the goal, no way it could work: Tier 2 with the reason. Then the usage checks: last used over 30 days ago, or still paying and not using: Tier 2 (not being used). Then the overlap check: two or more items from the same overlap group: Tier 2 (overlaps with something else) for the one used less. The person is always shown both and asked which they'd keep.
A36: 5. Wearable can see it, acts fast, effect at least 0.8? | B36: Tier 1. Order the person's Tier 1 list by expected effect, largest first. Check the 'read from history' column: if the app already has weeks of on and off nights from tags or workouts, show that comparison as a day-one hypothesis before the test.
A37: 6. Wearable can see it, acts fast, effect under 0.8? | B37: Tier 3, 'effect too small to see in two weeks', with the option to run it anyway.
A38: 7. Wearable can see it but it's slow? | B38: Tier 1 in principle, queued. Never run 3-day blocks on it.
A39: 8. Everything else | B39: Tier 3. Daily rating offered only for goals you'd feel rather than measure.
A41: How the effect numbers were made, and how much to trust them
A42: Each is the typical published effect for the row's main number, divided by a typical person's normal night-to-night swing for that number (see the 'Numbers we can watch' sheet). Where the effect depends on the person (a hot sleeper, a snorer, someone with night bathroom trips), the 'where the estimate comes from' column says what number to use instead. These are working estimates from the literature as I know it, not a meta-analysis, and every one of them is a fair target for the team to challenge. The gate at 0.8 is a judgement call: at 0.8, seven nights a side gives roughly a one-in-three chance of a clear answer; at 1.2 it's better than even.
A44: 'What are you about to buy?' Free stand-in tests
A45: Sauna | B45: Hot bath or shower 1 to 2 hours before bed, 14 days. Same mechanism.
A46: Cold plunge tub | B46: Cold shower, 14 days. If HRV doesn't notice the shower, the tub won't change that.
A47: Eight Sleep or cooling pad | B47: Thermostat down 2 degrees plus a fan, 14 days.
A48: Red light panel (for sleep) | B48: Ten minutes of morning sunlight, week-long blocks.
A49: Weighted blanket | B49: Heaviest duvet already owned, 3 on and 3 off.
A50: Mattress | B50: No stand-in. The shop's 100-night trial is the test.
A51: Any supplement | B51: One month at the studied dose, then the row's test.
A52: Glucose monitor (no diabetes) | B52: No stand-in and no evidence. The verdict is the annual cost.
A54: What each column on the Items sheet means
A55: Key | B55: A stable code for the engine. Doesn't change when the item is renamed.
A56: Cost per month / per year | B56: US retail estimate, prefilled in onboarding and editable. One-off devices are spread over 24 months. Per year is a live formula.
A57: Can a wearable see it? | B57: yes = a number changes the same night. partial = weakly, or for some goals. no = blind.
A58: Which number we'd watch | B58: Chosen before the test and never changed after.
A59: How fast it acts and clears | B59: fast = hours, so 3-day blocks work. slow = weeks, so they don't.
A60: Expected effect | B60: How big the change is likely to be, in units of that person's normal night-to-night swing. 1.0 means 'about as big as a normal bad night versus a normal good night'.
A61: Chance of a clear answer in two weeks | B61: good (1.2 and up), fair (0.8 to 1.2), low (under 0.8), or not applicable.
A62: Tier / Tier after the effect gate | B62: The first is the row's natural tier. The second is what the engine actually uses, after the 0.8 gate and the slow-item queue.
A63: Can we read it from their history? | B63: Whether the wearable's past data already shows on and off nights for this item.
A64: On-days: assigned or observed? | B64: assign = we set the schedule. observe only = we never assign an on-day (alcohol, nicotine, cannabis); we record it when it happens.
A65: Evidence grade | B65: A = well-run trials agree, measured properly. B = proper trials but small, mixed, or based on how people felt. C = a few small trials or studies that only watched people. D = stories, marketing, lab-dish or animal only. N = tested properly and found to do nothing.
A66: What the user reads on day one | B66: The actual sentence, in the product's voice. Read the Tone Guide and Emotional Positioning sheets before changing any.
... A68: Needs a fact-check? / What to check | B68: yes on every Tier 2 row and every row with a specific number. The note says what to verify and where to look. Nothing in this file is a citation; these are the citations to go and get.

Sheet Items
A1: # | B1: Key | C1: Item | D1: Do, buy, or environment | E1: Category | F1: Cost per month (USD) | G1: Cost per year (USD) | H1: Typical amount or how often | I1: What people usually take it for | J1: Can a wearable see it? | K1: Which number we'd watch | L1: Which way it should move | M1: How fast it acts and clears | N1: How we'd test it | O1: Can we run it this semester? | P1: Expected effect (in units of a normal night-to-night swing) | Q1: Where the effect estimate comes from | R1: Chance of a clear answer in two weeks | S1: Tier | T1: Tier name | U1: Tier after the effect gate (what the engine uses) | V1: Can we read it from their history? | W1: On-days: assigned or observed? | X1: Lowest dose worth testing (below this = day-one drop) | Y1: Evidence grade | Z1: What the studies actually found | AA1: Is there a known way it could work? | AB1: Why it's a day-one drop (Tier 2 only) | AC1: How the answer changes with the person's goal or situation | AD1: Follow-up question (trigger) | AE1: Question wording | AF1: Answer options | AG1: Rule that flips the tier (threshold) | AH1: Overlap group | AI1: Safety note (shown with the verdict) | AJ1: What the user reads on day one | AK1: Needs a fact-check? | AL1: What to check, and where to look
A2: 1 | B2: magnesium-any-form | C2: Magnesium (any form) | D2: buy | E2: supplement | F2: 22 | G2: =F2*12 -> 264 | H2: 200–400 mg elemental, evening | I2: sleep, relaxation, cramps | J2: yes | K2: Time to fall asleep; deep sleep | L2: fall asleep faster | M2: fast: acts and clears within hours | N2: 3 days on, 3 days off, for 14 days | O2: yes | P2: 0.3 | Q2: About 5 min faster to fall asleep in people who were low in magnesium; near zero in everyone else. Deep sleep does not move. | R2: low | S2: 1 | T2: Tested on you | U2: 3, effect too small | V2: yes, if they've been tagging it in Oura or WHOOP | W2: assign (we set the on and off days) | X2: ≥200 mg elemental (sleep trials used 320–500 mg) | Y2: B | Z2: Small trials found people fell asleep about 15 minutes faster, mostly older adults or people who were low in magnesium to begin with. The effect on deep sleep and other stages is small or absent. | AA2: yes | AC2: Goal sleep: Tier 1. Goal cramps or 'general': Tier 3. Dose under 200 mg elemental: Tier 2 (dose too low). | AD2: dose & form | AE2: Which form, and how much a day? | AF2: glycinate · citrate · malate · threonate · oxide · spray or oil · not sure; dose in mg elemental | AG2: form = oxide or spray → Tier 2 (form not absorbed). form = glycinate, citrate, malate, threonate AND dose under 200 mg elemental → Tier 2 (dose too low). Otherwise goal sleep → Tier 3 (effect too small, can run anyway); goal cramps or general → Tier 3. | AH2: sleep aids, magnesium | AI2: Loose stools at high doses. Kidney disease: ask a clinician first. | AJ2: Where it worked in trials, the change was a few minutes, mostly in people low in magnesium. That's about a third of one night's normal swing, so a two-week test would very likely come back inconclusive. We'll show you what the trials found and what it costs, and if you'd still like to run it, you can, knowing that going in. | AK2: no
A3: 2 | B3: magnesium-spray-oil-transdermal | C3: Magnesium spray / oil (transdermal) | D3: buy | E3: supplement | F3: 15 | G3: =F3*12 -> 180 | H3: nightly | I3: sleep, cramps | J3: yes | K3: Time to fall asleep | M3: fast: acts and clears within hours | N3: no experiment | O3: no | P3: 0 | Q3: Tier 2; not absorbed. | R3: not tested | S3: 2 | T3: No test needed | U3: 2 | V3: no | X3: no absorbed dose established | Y3: N | Z3: No controlled study has shown that magnesium gets through skin in a meaningful amount. The one small trial claiming it did wasn't blinded, meaning people knew what they were getting. | AA3: no | AB3: no way it could work | AC3: Always Tier 2. | AD3: none | AE3: (no question) | AF3: Routes on the item name alone. | AG3: Routes on the item name alone. | AJ3: There's no evidence magnesium gets through skin in a meaningful amount. If the ritual is part of your wind-down, that's real and it's yours. The $15 a month for the magnesium itself isn't doing anything. | AK3: yes | AL3: That no controlled study shows skin absorption. Look for: Gröber 2017 review of transdermal magnesium.
A4: 3 | B4: magnesium-l-threonate | C4: Magnesium L-threonate | D4: buy | E4: supplement | F4: 40 | G4: =F4*12 -> 480 | H4: 1–2 g product (~144 mg elemental) | I4: sleep, cognition | J4: yes | K4: Deep sleep; time to fall asleep | L4: improve | M4: fast: acts and clears within hours | N4: 3 days on, 3 days off, for 14 days | O4: yes | P4: 0.3 | Q4: One small seller-funded trial. | R4: low | S4: 1 | T4: Tested on you | U4: 3, effect too small | V4: yes, if they've been tagging it in Oura or WHOOP | W4: assign (we set the on and off days) | X4: ≥1 g product | Y4: C | Z4: One small trial, paid for by the seller, found a modest sleep improvement in adults. The claims about thinking and memory come from data in rats. | AA4: weak | AC4: Goal sleep: Tier 1. Goal cognition: Tier 3 (focus rating). | AD4: dose & form | AE4: Which form, and how much a day? | AF4: dose in g of product | AG4: dose under 1 g of product a day → Tier 2 (dose too low). Otherwise Tier 3 (effect too small, can run anyway). | AH4: magnesium | AJ4: The one trial found a modest change, and the company paid for it. That's about a third of one night's normal swing, so a two-week test would very likely come back inconclusive. We'll show you what the trials found and what it costs, and if you'd still like to run it, you can, knowing that going in. | AK4: yes | AL4: The one adult sleep trial and its funding. Look for: Hausenblas 2024 (Neurocentria-funded).
A5: 4 | B5: melatonin | C5: Melatonin | D5: buy | E5: supplement | F5: 10 | G5: =F5*12 -> 120 | H5: 0.3–5 mg, 30–60 min before bed | I5: time to fall asleep, jet lag | J5: yes | K5: Time to fall asleep | L5: fall asleep faster | M5: fast: acts and clears within hours | N5: 3 days on, 3 days off, for 14 days | O5: yes | P5: 0.8 | Q5: About 7 min faster to fall asleep against a 10-min swing, so 0.7 for most people. Use 1.2 if the person takes over 30 min to fall asleep or has a shifted schedule (that's who it works for). | R5: fair | S5: 1 | T5: Tested on you | U5: 1 | V5: yes, if they've been tagging it in Oura or WHOOP | W5: assign (we set the on and off days) | X5: 0.3 mg is already active; more is not better | Y5: B | Z5: Reviews that pool many trials say it helps people fall asleep about 7 minutes faster and sleep about 8 minutes longer. It works well for jet lag and shifted schedules, less well for ordinary trouble sleeping. Taking more than 1 mg adds grogginess, not effect. | AA5: yes | AC5: Tier 1. If dose > 5 mg, verdict adds the 'less is more' line. | AD5: dose & form | AE5: Which form, and how much a day? | AF5: 0.3 · 0.5 · 1 · 3 · 5 · 10 mg; gummy or tablet | AG5: No tier flip. dose over 1 mg → verdict adds the 'less is more' line. dose over 5 mg → safety note. | AH5: sleep aids | AI5: Gummy doses are often mislabeled. Ask a clinician before nightly long-term use, for teens, or in pregnancy. | AJ5: Testable. The interesting question isn't whether it works, it's whether you need it every night or only when your schedule shifts. | AK5: yes | AL5: 7 and 8 minute figures. Look for: Ferracioli-Oda 2013 meta-analysis.
A6: 5 | B6: l-theanine | C6: L-theanine | D6: buy | E6: supplement | F6: 16 | G6: =F6*12 -> 192 | H6: 100–400 mg | I6: sleep, calm, focus with caffeine | J6: partial | K6: Time to fall asleep; overnight HRV | L6: fall asleep faster / HRV up | M6: fast: acts and clears within hours | N6: 3 days on, 3 days off, for 14 days | O6: yes | P6: 0.2 | Q6: Measured sleep changes are small and inconsistent. | R6: low | S6: 1 | T6: Tested on you | U6: 3, effect too small | V6: yes, if they've been tagging it in Oura or WHOOP | W6: assign (we set the on and off days) | X6: ≥200 mg | Y6: C | Z6: Trials found people said they felt less stressed. Measured changes in sleep were small and inconsistent. The best evidence is for taking the edge off caffeine when you take the two together. | AA6: yes | AC6: Goal sleep: Tier 1. Goal calm/focus: Tier 3 (rating). Dose under 100 mg: Tier 2 (dose too low). | AD6: dose & form | AE6: Which form, and how much a day? | AF6: mg | AG6: dose under 100 mg → Tier 2 (dose too low). Otherwise Tier 3 (effect too small, can run anyway). | AH6: sleep aids | AJ6: The measured sleep changes in trials are small and inconsistent. That's about a fifth of one night's normal swing, so a two-week test would very likely come back inconclusive. We'll show you what the trials found and what it costs, and if you'd still like to run it, you can, knowing that going in. | AK6: no
A7: 6 | B7: glycine | C7: Glycine | D7: buy | E7: supplement | F7: 12 | G7: =F7*12 -> 144 | H7: 3 g before bed | I7: sleep quality | J7: yes | K7: Time to fall asleep; deep sleep | L7: improve | M7: fast: acts and clears within hours | N7: 3 days on, 3 days off, for 14 days | O7: yes | P7: 0.4 | Q7: Two tiny trials; a few minutes faster to fall asleep. | R7: low | S7: 1 | T7: Tested on you | U7: 3, effect too small | V7: yes, if they've been tagging it in Oura or WHOOP | W7: assign (we set the on and off days) | X7: ≥3 g | Y7: C | Z7: Two small Japanese trials, about 20 people each, found people fell asleep faster and felt less tired the next day on 3 g. Nothing bigger has been done since. | AA7: yes | AC7: Dose under 1 g: Tier 2 (dose too low). Otherwise Tier 1. | AD7: dose & form | AE7: Which form, and how much a day? | AF7: g | AG7: dose under 1 g → Tier 2 (dose too low). Otherwise Tier 3 (effect too small, can run anyway). | AH7: sleep aids | AJ7: Two tiny trials found a few minutes' difference. That's about two fifths of one night's normal swing, so a two-week test would very likely come back inconclusive. We'll show you what the trials found and what it costs, and if you'd still like to run it, you can, knowing that going in. | AK7: yes | AL7: The 3 g trials. Look for: Yamadera 2007; Inagawa 2006.
A8: 7 | B8: apigenin | C8: Apigenin | D8: buy | E8: supplement | F8: 20 | G8: =F8*12 -> 240 | H8: 50 mg | I8: sleep | J8: yes | K8: Time to fall asleep; deep sleep | L8: improve | M8: fast: acts and clears within hours | N8: 3 days on, 3 days off, for 14 days | O8: yes | P8: 0.1 | Q8: No human trial; nothing to expect. | R8: low | S8: 1 | T8: Tested on you | U8: 3, effect too small | V8: yes, if they've been tagging it in Oura or WHOOP | W8: assign (we set the on and off days) | X8: no human dose established | Y8: D | Z8: There has never been a human trial of apigenin on its own for sleep. It became popular because of one podcast protocol and some lab-dish work on brain receptors. | AA8: weak | AC8: Tier 1 (it's testable). Verdict notes the evidence is a podcast, not a trial. | AD8: overlap (automatic) | AE8: (no question) | AF8: Fires on its own when two or more items from the same overlap group are both in the inventory. The person is shown both and asked which one they'd keep. | AG8: Routes on the item name alone. | AH8: sleep aids | AJ8: There has never been a human trial, so there's no effect size to expect. That's about a tenth of one night's normal swing, so a two-week test would very likely come back inconclusive. We'll show you what the trials found and what it costs, and if you'd still like to run it, you can, knowing that going in. | AK8: no
A9: 8 | B9: ashwagandha-ksm-66-sensoril | C9: Ashwagandha (KSM-66 / Sensoril) | D9: buy | E9: supplement | F9: 19 | G9: =F9*12 -> 228 | H9: 300–600 mg root extract daily | I9: stress, sleep, cortisol | J9: partial | K9: Overnight HRV; time to fall asleep | L9: HRV up | M9: slow: builds up or clears over weeks | N9: 2 weeks on, 2 weeks off (not this semester) | O9: no | P9: 0.5 | Q9: Modest sleep and HRV changes after 6 to 8 weeks. Long blocks only. | R9: not in two weeks | S9: 1 | T9: Tested on you | U9: 1, queued (slow) | V9: no | W9: assign (we set the on and off days) | X9: ≥300 mg standardised extract | Y9: B | Z9: Several trials lasting 6 to 8 weeks found people said they felt less stressed and slept a bit better. The effect builds over weeks, not nights. | AA9: yes | AC9: Slow: long blocks only. v1: honest 'can't test in 14 days' plus evidence line. Dose under 250 mg: Tier 2 (dose too low). | AD9: dose & form | AE9: Which form, and how much a day? | AF9: KSM-66 · Sensoril · other extract · plain root powder · not sure; dose in mg | AG9: form = plain root powder under 1 g, or extract under 250 mg → Tier 2 (dose too low). Otherwise Tier 1, queued (slow). | AI9: Rare liver injury reports; can raise thyroid hormone. Avoid in pregnancy. Stop and ask a clinician if you get nausea or dark urine. | AJ9: This one works slowly, so a two-week on/off test would be unfair to it. We'll tell you what the trials found, and queue it for a longer test when we can run one. | AK9: yes | AL9: Liver injury and thyroid reports. Look for: LiverTox (NIH) entry on ashwagandha.
A10: 9 | B10: valerian | C10: Valerian | D10: buy | E10: supplement | F10: 12 | G10: =F10*12 -> 144 | H10: 300–600 mg | I10: sleep | J10: yes | K10: Time to fall asleep | L10: fall asleep faster | M10: fast: acts and clears within hours | N10: 3 days on, 3 days off, for 14 days | O10: yes | P10: 0.2 | Q10: Measured sleep mostly unchanged in trials. | R10: low | S10: 1 | T10: Tested on you | U10: 3, effect too small | V10: yes, if they've been tagging it in Oura or WHOOP | W10: assign (we set the on and off days) | X10: ≥300 mg | Y10: C | Z10: Trials are mixed. People sometimes say they slept better, but their measured sleep mostly didn't change. | AA10: weak | AC10: Tier 1. | AD10: dose & form | AE10: Which form, and how much a day? | AF10: mg | AG10: dose under 300 mg → Tier 2 (dose too low). Otherwise Tier 3 (effect too small, can run anyway). | AH10: sleep aids | AJ10: In trials, people felt they slept better while their measured sleep stayed the same. That's about a fifth of one night's normal swing, so a two-week test would very likely come back inconclusive. We'll show you what the trials found and what it costs, and if you'd still like to run it, you can, knowing that going in. | AK10: no
A11: 10 | B11: chamomile-tea | C11: Chamomile tea | D11: buy | E11: food/drink | F11: 8 | G11: =F11*12 -> 96 | H11: 1 cup nightly | I11: sleep, wind-down | J11: yes | K11: Time to fall asleep | L11: fall asleep faster | M11: fast: acts and clears within hours | N11: 3 days on, 3 days off, for 14 days | O11: yes | P11: 0.2 | Q11: Measured sleep unchanged; people feel calmer. | R11: low | S11: 1 | T11: Tested on you | U11: 3, effect too small | V11: yes, if they've been tagging it in Oura or WHOOP | W11: assign (we set the on and off days) | X11: no dose rule | Y11: C | Z11: Small trials found people said they slept slightly better, but their measured sleep didn't reliably change. The warm drink and the routine may be most of what's working. | AA11: weak | AC11: Tier 1. Cheap and enjoyed: verdict says keep regardless of result. | AD11: overlap (automatic) | AE11: (no question) | AF11: Fires on its own when two or more items from the same overlap group are both in the inventory. The person is shown both and asked which one they'd keep. | AG11: Routes on the item name alone. | AH11: sleep aids | AJ11: People feel calmer; the sleep numbers don't change. That's about a fifth of one night's normal swing, so a two-week test would very likely come back inconclusive. We'll show you what the trials found and what it costs, and if you'd still like to run it, you can, knowing that going in. | AK11: no
A12: 11 | B12: sleep-tea-blend-valerian-passionflower-lemon-balm | C12: Sleep tea blend (valerian, passionflower, lemon balm) | D12: buy | E12: food/drink | F12: 17 | G12: =F12*12 -> 204 | H12: nightly | I12: sleep | J12: yes | K12: Time to fall asleep | L12: fall asleep faster | M12: fast: acts and clears within hours | N12: 3 days on, 3 days off, for 14 days | O12: yes | P12: 0.2 | Q12: As the individual herbs. | R12: low | S12: 1 | T12: Tested on you | U12: 3, effect too small | V12: yes, if they've been tagging it in Oura or WHOOP | W12: assign (we set the on and off days) | X12: no dose rule | Y12: C | Z12: Each herb has small, mixed trials. Blends are untested as products. | AA12: weak | AC12: Tier 1. | AD12: overlap (automatic) | AE12: (no question) | AF12: Fires on its own when two or more items from the same overlap group are both in the inventory. The person is shown both and asked which one they'd keep. | AG12: Routes on the item name alone. | AH12: sleep aids | AJ12: Each herb has small trials, and none moved the numbers much. That's about a fifth of one night's normal swing, so a two-week test would very likely come back inconclusive. We'll show you what the trials found and what it costs, and if you'd still like to run it, you can, knowing that going in. | AK12: no
A13: 12 | B13: tart-cherry-juice-extract | C13: Tart cherry juice / extract | D13: buy | E13: supplement | F13: 30 | G13: =F13*12 -> 360 | H13: 240 ml twice daily or 480 mg extract | I13: sleep, recovery | J13: yes | K13: Total sleep | L13: up | M13: fast: acts and clears within hours | N13: 3 days on, 3 days off, for 14 days | O13: yes | P13: 0.4 | Q13: Tiny trials claim 30 to 80 min; a realistic guess after shrinking for tiny-study inflation is under half a swing. | R13: low | S13: 1 | T13: Tested on you | U13: 3, effect too small | V13: yes, if they've been tagging it in Oura or WHOOP | W13: assign (we set the on and off days) | X13: ≥240 ml juice or 480 mg extract | Y13: C | Z13: Two tiny trials, 8 to 20 people, reported 30 to 80 extra minutes of sleep. No bigger study has repeated the result. It contains a small amount of natural melatonin. | AA13: yes | AC13: Tier 1. | AD13: dose & form | AE13: Which form, and how much a day? | AF13: juice (ml a day) · extract (mg) | AG13: juice under 240 ml a day, or extract under 480 mg → Tier 2 (dose too low). Otherwise Tier 3 (effect too small, can run anyway). | AI13: About 25 g sugar per serving of juice. | AJ13: The tiny trials claimed a lot; the realistic expectation is under half a night's swing. That's about two fifths of one night's normal swing, so a two-week test would very likely come back inconclusive. We'll show you what the trials found and what it costs, and if you'd still like to run it, you can, knowing that going in. | AK13: yes | AL13: Trial sizes. Look for: Howatson 2012 (n=20); Losso 2018 (n=8).
A14: 13 | B14: cbd | C14: CBD | D14: buy | E14: supplement | F14: 45 | G14: =F14*12 -> 540 | H14: 10–50 mg gummies or oil | I14: sleep, anxiety | J14: yes | K14: Time to fall asleep; time awake during the night | L14: improve | M14: fast: acts and clears within hours | N14: 3 days on, 3 days off, for 14 days | O14: yes | P14: 0.3 | Q14: Mixed trials at doses higher than most products. | R14: low | S14: 1 | T14: Tested on you | U14: 3, effect too small | V14: yes, if they've been tagging it in Oura or WHOOP | W14: assign (we set the on and off days) | X14: ≥25 mg (trials used 25–160 mg and more) | Y14: C | Z14: The sleep trials used much higher doses than most gummies contain, and even then the results were mixed. The dose on the label is often wrong. | AA14: weak | AC14: Dose under 25 mg: Tier 2 (dose too low). Otherwise Tier 1. | AD14: dose & form | AE14: Which form, and how much a day? | AF14: mg per serving; gummy · oil · capsule | AG14: dose under 25 mg → Tier 2 (dose too low). Otherwise Tier 3 (effect too small, can run anyway). Any medication → Protected. | AH14: sleep aids | AI14: Interacts with some medications (blood thinners, some antidepressants). Check. | AJ14: At the doses in most products, the trials found little. That's about a third of one night's normal swing, so a two-week test would very likely come back inconclusive. We'll show you what the trials found and what it costs, and if you'd still like to run it, you can, knowing that going in. | AK14: yes | AL14: Dose gap between products and trials. Look for: Shannon 2019 (25 to 175 mg); product testing reports on mislabelling.
A15: 14 | B15: thc-cannabis-for-sleep | C15: THC / cannabis for sleep | D15: buy | E15: supplement | F15: 60 | G15: =F15*12 -> 720 | H15: nightly | I15: sleep | J15: yes | K15: Time to fall asleep; REM | L15: fall asleep faster / REM down | M15: fast: acts and clears within hours | N15: stop once, wait a week, then compare | O15: no | P15: 1.2 | Q15: 15 min faster to fall asleep and a clear REM drop, but the catch-up effect on stopping breaks the 3/3 test. Special design only. | R15: not in two weeks | S15: 1 | T15: Tested on you | U15: 1, queued (special design) | V15: yes, if they've been tagging it in Oura or WHOOP | W15: observe only (never assign an on-day) | X15: no dose rule | Y15: C | Z15: It helps you fall asleep faster in the short term and cuts down REM sleep. When you stop, you get several nights of REM catch-up and worse sleep. That catch-up effect makes a simple on/off test give the wrong answer. | AA15: yes | AC15: Not alternation-compatible (rebound). v1: report evidence only. Later: single switch with 7-night washout. | AD15: nights a week | AE15: How many nights a week, usually? | AF15: 0 · 1 to 2 · 3 to 4 · 5 or more. Asked plainly, no comment, no follow-up. | AG15: Routes on the item name alone. | AI15: Legal status varies. Nightly use builds tolerance; withdrawal insomnia is real and temporary. | AJ15: We can't run this as a 3-on/3-off test, because the off nights after nightly use are worse for everyone, and that would make the cannabis look like it 'works'. That would be a dishonest result, so we won't give you one. | AK15: yes | AL15: REM suppression and rebound. Look for: Babson 2017 review.
A16: 15 | B16: kava | C16: Kava | D16: buy | E16: supplement | F16: 30 | G16: =F16*12 -> 360 | H16: tea or capsule, evening | I16: anxiety, sleep | J16: yes | K16: Time to fall asleep | L16: fall asleep faster | M16: fast: acts and clears within hours | N16: 3 days on, 3 days off, for 14 days | O16: yes | P16: 0.4 | Q16: Anxiety evidence is decent; sleep evidence is thin. | R16: low | S16: 1 | T16: Tested on you | U16: 3, effect too small | V16: yes, if they've been tagging it in Oura or WHOOP | W16: assign (we set the on and off days) | X16: no dose rule | Y16: B | Z16: Decent evidence from proper trials that it helps with anxiety in the short term. The evidence for sleep is thin. | AA16: yes | AC16: Goal sleep: Tier 1. Goal anxiety: Tier 3 (mood rating). | AD16: overlap (automatic) | AE16: (no question) | AF16: Fires on its own when two or more items from the same overlap group are both in the inventory. The person is shown both and asked which one they'd keep. | AG16: Any alcohol most nights, or liver condition → safety note, Tier 3. | AH16: sleep aids | AI16: Liver injury has been reported. Avoid with alcohol or liver conditions. | AJ16: Decent for anxiety; thin for sleep. That's about two fifths of one night's normal swing, so a two-week test would very likely come back inconclusive. We'll show you what the trials found and what it costs, and if you'd still like to run it, you can, knowing that going in. | AK16: yes | AL16: Liver warnings. Look for: FDA 2002 consumer advisory; LiverTox.
A17: 16 | B17: passionflower | C17: Passionflower | D17: buy | E17: supplement | F17: 12 | G17: =F17*12 -> 144 | H17: capsule or tea | I17: sleep, anxiety | J17: yes | K17: Time to fall asleep | L17: fall asleep faster | M17: fast: acts and clears within hours | N17: 3 days on, 3 days off, for 14 days | O17: yes | P17: 0.2 | Q17: One small trial of tea. | R17: low | S17: 1 | T17: Tested on you | U17: 3, effect too small | V17: yes, if they've been tagging it in Oura or WHOOP | W17: assign (we set the on and off days) | X17: no dose rule | Y17: C | Z17: One small trial of the tea found people said they slept slightly better. | AA17: weak | AC17: Tier 1. | AD17: overlap (automatic) | AE17: (no question) | AF17: Fires on its own when two or more items from the same overlap group are both in the inventory. The person is shown both and asked which one they'd keep. | AG17: Routes on the item name alone. | AH17: sleep aids | AJ17: One small trial of the tea found a small difference in how people felt. That's about a fifth of one night's normal swing, so a two-week test would very likely come back inconclusive. We'll show you what the trials found and what it costs, and if you'd still like to run it, you can, knowing that going in. | AK17: no
A18: 17 | B18: lemon-balm | C18: Lemon balm | D18: buy | E18: supplement | F18: 12 | G18: =F18*12 -> 144 | H18: capsule or tea | I18: sleep, calm | J18: yes | K18: Time to fall asleep | L18: fall asleep faster | M18: fast: acts and clears within hours | N18: 3 days on, 3 days off, for 14 days | O18: yes | P18: 0.2 | Q18: Small trials, mostly how people felt. | R18: low | S18: 1 | T18: Tested on you | U18: 3, effect too small | V18: yes, if they've been tagging it in Oura or WHOOP | W18: assign (we set the on and off days) | X18: no dose rule | Y18: C | Z18: Small trials, mostly people saying they felt calmer. | AA18: weak | AC18: Tier 1. | AD18: overlap (automatic) | AE18: (no question) | AF18: Fires on its own when two or more items from the same overlap group are both in the inventory. The person is shown both and asked which one they'd keep. | AG18: Routes on the item name alone. | AH18: sleep aids | AJ18: Small trials, mostly about how people felt. That's about a fifth of one night's normal swing, so a two-week test would very likely come back inconclusive. We'll show you what the trials found and what it costs, and if you'd still like to run it, you can, knowing that going in. | AK18: no
A19: 18 | B19: 5-htp | C19: 5-HTP | D19: buy | E19: supplement | F19: 15 | G19: =F19*12 -> 180 | H19: 50–200 mg | I19: sleep, mood | J19: yes | K19: Time to fall asleep; REM | L19: improve | M19: fast: acts and clears within hours | N19: 3 days on, 3 days off, for 14 days | O19: yes | P19: 0.2 | Q19: Small trials. | R19: low | S19: 1 | T19: Tested on you | U19: 3, effect too small | V19: yes, if they've been tagging it in Oura or WHOOP | W19: assign (we set the on and off days) | X19: ≥100 mg | Y19: C | Z19: Small trials. The evidence for mood is a little stronger than for sleep. | AA19: yes | AC19: Goal sleep: Tier 1. Goal mood: Tier 3 (rating). On any antidepressant: Protected. | AD19: dose & form | AE19: Which form, and how much a day? | AF19: mg | AG19: dose under 100 mg → Tier 2 (dose too low). On an antidepressant → Protected. | AH19: sleep aids | AI19: Do not combine with antidepressants (serotonin syndrome risk). | AJ19: The sleep trials are small. That's about a fifth of one night's normal swing, so a two-week test would very likely come back inconclusive. We'll show you what the trials found and what it costs, and if you'd still like to run it, you can, knowing that going in. | AK19: no
A20: 19 | B20: gaba-oral | C20: GABA (oral) | D20: buy | E20: supplement | F20: 15 | G20: =F20*12 -> 180 | H20: 500–750 mg | I20: sleep, calm | J20: yes | K20: Time to fall asleep | M20: fast: acts and clears within hours | N20: no experiment | O20: no | P20: 0 | Q20: Tier 2; can't reach the brain. | R20: not tested | S20: 2 | T20: No test needed | U20: 2 | V20: no | X20: no dose rule | Y20: D | Z20: Swallowed GABA mostly can't get past the barrier that protects the brain. The small trials that exist were paid for by the sellers and don't agree with each other. | AA20: no | AB20: no way it could work | AC20: Tier 2. | AD20: none | AE20: (no question) | AF20: Routes on the item name alone. | AG20: Routes on the item name alone. | AJ20: The reason this probably isn't working is that swallowed GABA mostly can't reach the brain. That's chemistry, not you. | AK20: yes | AL20: Barrier claim and seller funding of the trials. Look for: Boonstra 2015 review of oral GABA.
A21: 20 | B21: lavender-oil-oral-silexan | C21: Lavender oil, oral (Silexan) | D21: buy | E21: supplement | F21: 25 | G21: =F21*12 -> 300 | H21: 80 mg | I21: anxiety, sleep | J21: partial | K21: Time to fall asleep | L21: fall asleep faster | M21: fast: acts and clears within hours | N21: 3 days on, 3 days off, for 14 days | O21: yes | P21: 0.4 | Q21: Sleep improves alongside anxiety; modest in the numbers. | R21: low | S21: 1 | T21: Tested on you | U21: 3, effect too small | V21: yes, if they've been tagging it in Oura or WHOOP | W21: assign (we set the on and off days) | X21: 80 mg | Y21: B | Z21: Decent trials for anxiety. People's sleep improved alongside their anxiety. | AA21: yes | AC21: Goal sleep: Tier 1. Goal anxiety: Tier 3 (rating). | AD21: dose & form | AE21: Which form, and how much a day? | AF21: Silexan 80 mg · other oral lavender · essential oil | AG21: form = anything other than Silexan 80 mg (e.g. a generic lavender capsule or essential oil taken by mouth) → Tier 2 (form not absorbed) with a safety note about swallowing essential oils. | AH21: sleep aids | AJ21: Sleep improves a little alongside anxiety. That's about two fifths of one night's normal swing, so a two-week test would very likely come back inconclusive. We'll show you what the trials found and what it costs, and if you'd still like to run it, you can, knowing that going in. | AK21: no
A22: 21 | B22: sleep-gummies-blend | C22: Sleep gummies (blend) | D22: buy | E22: supplement | F22: 20 | G22: =F22*12 -> 240 | H22: nightly | I22: sleep | J22: yes | K22: Time to fall asleep | L22: fall asleep faster | M22: fast: acts and clears within hours | N22: 3 days on, 3 days off, for 14 days | O22: yes | P22: 0.6 | Q22: The melatonin in it, usually at a higher-than-useful dose. | R22: low | S22: 1 | T22: Tested on you | U22: 3, effect too small | V22: yes, if they've been tagging it in Oura or WHOOP | W22: assign (we set the on and off days) | X22: depends on melatonin content | Y22: B | Z22: Usually melatonin plus tiny amounts of herbs. The melatonin is what's working. The dose on gummy labels is often wrong. | AA22: yes | AC22: Tier 1. Verdict notes plain melatonin at 0.5 mg is a third of the price. | AD22: dose & form | AE22: Which form, and how much a day? | AF22: melatonin mg per gummy, from the label | AG22: melatonin content over 3 mg → verdict adds the 'less is more' line. Contains no melatonin → route as the herb blend (Tier 3, effect too small). | AH22: sleep aids | AJ22: It's the melatonin doing the work, and for most people that's a few minutes. That's about three fifths of one night's normal swing, so a two-week test would very likely come back inconclusive. We'll show you what the trials found and what it costs, and if you'd still like to run it, you can, knowing that going in. | AK22: yes | AL22: Gummy mislabelling. Look for: Cohen 2023, JAMA (melatonin gummies).
A23: 22 | B23: zma | C23: ZMA | D23: buy | E23: supplement | F23: 20 | G23: =F23*12 -> 240 | H23: zinc 30 mg, magnesium 450 mg, B6 | I23: sleep, testosterone, recovery | J23: yes | K23: Deep sleep | L23: up | M23: fast: acts and clears within hours | N23: 3 days on, 3 days off, for 14 days | O23: yes | P23: 0.3 | Q23: As magnesium. | R23: low | S23: 1 | T23: Tested on you | U23: 3, effect too small | V23: yes, if they've been tagging it in Oura or WHOOP | W23: assign (we set the on and off days) | X23: no dose rule | Y23: N | Z23: The testosterone claim was never repeated by other researchers. Any sleep effect is the magnesium. | AA23: weak | AC23: Goal testosterone: Tier 2 (tested, found nothing). Goal sleep: Tier 1 as magnesium. | AD23: overlap (automatic) | AE23: (no question) | AF23: Fires on its own when two or more items from the same overlap group are both in the inventory. The person is shown both and asked which one they'd keep. | AG23: Routes on the item name alone. | AH23: magnesium | AJ23: The magnesium part might do a little; the rest does nothing measurable. That's about a third of one night's normal swing, so a two-week test would very likely come back inconclusive. We'll show you what the trials found and what it costs, and if you'd still like to run it, you can, knowing that going in. | AK23: no
A24: 23 | B24: vitamin-d3 | C24: Vitamin D3 | D24: buy | E24: supplement | F24: 8 | G24: =F24*12 -> 96 | H24: 1,000–5,000 IU | I24: energy, immunity, mood, bone | J24: no | M24: slow: builds up or clears over weeks | N24: no experiment | O24: no | R24: not tested | S24: 3 | T24: Can't measure it | U24: 3 | V24: no | X24: no dose rule | Y24: B | Z24: Clearly useful if you're low in it, which is common in winter and for people with darker skin living far from the equator. In people whose levels are normal, large trials found little benefit for mood, energy or catching fewer colds. | AA24: yes | AC24: Source = doctor/blood test: Protected. Otherwise Tier 3 with a nudge to get a level. | AD24: dose & form | AE24: Which form, and how much a day? | AF24: IU a day | AG24: No tier flip on dose. dose over 10,000 IU a day → safety note. Source = doctor or blood test → Protected. | AH24: daily multivitamin | AI24: Very high doses (over 10,000 IU/day) long term can cause harm. | AJ24: We can't see this in your data, and we won't tell you to drop it, because if you're low it matters. A blood level costs about $30 and answers this properly. | AK24: yes | AL24: Large trials in non-deficient people. Look for: VITAL (Manson 2019); D-Health (Neale 2022).
A25: 24 | B25: vitamin-b12 | C25: Vitamin B12 | D25: buy | E25: supplement | F25: 8 | G25: =F25*12 -> 96 | H25: 500–1,000 mcg | I25: energy | J25: no | M25: slow: builds up or clears over weeks | N25: no experiment | O25: no | R25: not tested | S25: 2 | T25: No test needed | U25: 2 | V25: no | X25: no dose rule | Y25: N | Z25: In people who aren't low in it, B12 does nothing for energy, and that's been tested several times. Vegans, vegetarians, people over 60, and people on metformin or stomach-acid reducers are often low. | AA25: weak | AB25: tested, found nothing | AC25: Source = doctor/blood test, or user is vegan/vegetarian/60+: Tier 3 with 'get a level'. Otherwise Tier 2 (tested, found nothing). | AD25: overlap (automatic) | AE25: (no question) | AF25: Fires on its own when two or more items from the same overlap group are both in the inventory. The person is shown both and asked which one they'd keep. | AG25: Route on source and diet, not dose: vegan, vegetarian, over 60, on metformin or acid reducers, or doctor-sourced → Tier 3 'get a level'. Otherwise Tier 2 (tested, found nothing). | AH25: daily multivitamin | AJ25: If you eat meat and you're under 60, the energy you're hoping for isn't in this bottle; trials in people with normal levels are flat. If you're vegan or over 60, ignore that and get a level first. | AK25: yes | AL25: That trials in non-deficient people show no energy effect. Look for: Cochrane / systematic reviews of B12 supplementation in non-deficient adults.
A26: 25 | B26: b-complex | C26: B-complex | D26: buy | E26: supplement | F26: 10 | G26: =F26*12 -> 120 | H26: daily | I26: energy, stress | J26: no | M26: slow: builds up or clears over weeks | N26: no experiment | O26: no | R26: not tested | S26: 2 | T26: No test needed | U26: 2 | V26: no | X26: no dose rule | Y26: N | Z26: Same as B12: no effect on energy unless you're low in it. | AA26: weak | AB26: tested, found nothing | AC26: As B12. | AD26: overlap (automatic) | AE26: (no question) | AF26: Fires on its own when two or more items from the same overlap group are both in the inventory. The person is shown both and asked which one they'd keep. | AG26: Routes on the item name alone. | AH26: daily multivitamin | AJ26: Same as B12: without a deficiency, this isn't where energy comes from. | AK26: yes | AL26: Same as B12.
A27: 26 | B27: iron | C27: Iron | D27: buy | E27: supplement | F27: 8 | G27: =F27*12 -> 96 | H27: 18–65 mg | I27: energy, fatigue | J27: no | M27: slow: builds up or clears over weeks | N27: no experiment | O27: no | R27: not tested | S27: P | T27: Protected | U27: P | V27: no | X27: no dose rule | Y27: A | Z27: Life-changing if you're low in iron, which is common in women who menstruate and in endurance athletes. Harmful to take if you're not. | AA27: yes | AC27: Always Protected. Never routed to Tier 2. | AD27: none | AE27: (no question) | AF27: Routes on the item name alone. | AG27: Routes on the item name alone. | AI27: Iron without a confirmed low ferritin can cause harm. This needs a blood test, not an app. | AJ27: We don't touch iron. It's the one supplement that's either exactly what you need or something you shouldn't take, and only a ferritin test can say which. | AK27: yes | AL27: Harm from unneeded iron. Look for: NIH ODS iron fact sheet.
A28: 27 | B28: multivitamin | C28: Multivitamin | D28: buy | E28: supplement | F28: 15 | G28: =F28*12 -> 180 | H28: daily | I28: general health | J28: no | M28: slow: builds up or clears over weeks | N28: no experiment | O28: no | R28: not tested | S28: 3 | T28: Can't measure it | U28: 3 | V28: no | X28: no dose rule | Y28: C | Z28: Large trials in well-nourished adults show no effect on heart disease, cancer or mortality. Possibly a small cognitive benefit in older adults. | AA28: weak | AC28: Tier 3 (untestable). Verdict shows cost and evidence, no push either way. | AD28: overlap (automatic) | AE28: (no question) | AF28: Fires on its own when two or more items from the same overlap group are both in the inventory. The person is shown both and asked which one they'd keep. | AG28: Routes on the item name alone. | AH28: daily multivitamin | AJ28: Think of it as insurance. The big trials say it doesn't change much for people who eat reasonably well, and it also doesn't do any harm. Keep it or don't; either is a fine answer. | AK28: no
A29: 28 | B29: omega-3-fish-oil | C29: Omega-3 fish oil | D29: buy | E29: supplement | F29: 20 | G29: =F29*12 -> 240 | H29: 1–2 g EPA+DHA | I29: heart, mood, inflammation, joints | J29: no | M29: slow: builds up or clears over weeks | N29: no experiment | O29: no | R29: not tested | S29: 3 | T29: Can't measure it | U29: 3 | V29: no | X29: ≥1 g EPA+DHA combined (many capsules are 300 mg) | Y29: B | Z29: A modest benefit for blood fats, and possibly for mood, at 1 g a day and above. Most of the trials that found a benefit were in people who don't eat fish. | AA29: yes | AC29: EPA+DHA under 500 mg/day: Tier 2 (dose too low). Otherwise Tier 3. Source = doctor: Protected. | AD29: dose & form | AE29: Which form, and how much a day? | AF29: EPA + DHA in mg per capsule (back of the bottle), capsules a day | AG29: EPA + DHA combined under 500 mg a day → Tier 2 (dose too low). 500 mg to 1 g → Tier 3 with a 'below the studied dose' note. 1 g or more → Tier 3. | AH29: omega-3 | AI29: Blood thinners: check with prescriber. | AJ29: Check the back of the bottle for EPA + DHA, not 'fish oil'. Under 500 mg combined is a dose the trials never found anything at. At 1 g or more we can't see it in your data, but the evidence is decent. | AK29: yes | AL29: 1 g EPA+DHA threshold. Look for: AHA advisory; typical capsule contents.
A30: 29 | B30: krill-oil | C30: Krill oil | D30: buy | E30: supplement | F30: 30 | G30: =F30*12 -> 360 | H30: 500 mg | I30: heart, joints | J30: no | M30: slow: builds up or clears over weeks | N30: no experiment | O30: no | R30: not tested | S30: 2 | T30: No test needed | U30: 2 | V30: no | X30: ≥1 g EPA+DHA | Y30: B | Z30: The same omega-3 fats as fish oil, at a much smaller dose and several times the price. | AA30: yes | AB30: dose too low | AC30: Tier 2 (dose too low) unless taking 3+ capsules. | AD30: dose & form | AE30: Which form, and how much a day? | AF30: capsules a day; EPA + DHA per capsule | AG30: EPA + DHA under 1 g a day → Tier 2 (dose too low). Almost every krill product fires this at label dose. | AH30: omega-3 | AJ30: This is fish oil at a smaller dose and a higher price. If omega-3 is the goal, plain fish oil at 1 g EPA+DHA gets you what the trials used, for less. | AK30: yes | AL30: Typical EPA+DHA per capsule (about 100 to 150 mg) versus fish oil trial doses. Check three best-selling labels.
A31: 30 | B31: flaxseed-oil-as-omega-3 | C31: Flaxseed oil (as omega-3) | D31: buy | E31: supplement | F31: 12 | G31: =F31*12 -> 144 | H31: 1 tbsp | I31: omega-3, heart | J31: no | M31: slow: builds up or clears over weeks | N31: no experiment | O31: no | R31: not tested | S31: 2 | T31: No test needed | U31: 2 | V31: no | X31: no dose rule | Y31: N | Z31: Conversion of plant ALA to EPA/DHA is under 10%. Doesn't raise blood levels the way fish oil does. | AA31: weak | AB31: form not absorbed | AC31: Goal omega-3: Tier 2 (form not absorbed). As a food, fine. | AD31: overlap (automatic) | AE31: (no question) | AF31: Fires on its own when two or more items from the same overlap group are both in the inventory. The person is shown both and asked which one they'd keep. | AG31: Routes on the item name alone. | AH31: omega-3 | AJ31: Your body converts very little of this into the omega-3s fish oil provides. Fine as a food, not as a substitute. | AK31: yes | AL31: ALA to EPA/DHA conversion under 10%. Look for: Burdge & Calder 2005.
A32: 31 | B32: creatine-monohydrate | C32: Creatine monohydrate | D32: buy | E32: supplement | F32: 14 | G32: =F32*12 -> 168 | H32: 3–5 g daily | I32: strength, cognition, energy | J32: no | M32: slow: builds up or clears over weeks | N32: no experiment | O32: no | R32: not tested | S32: 3 | T32: Can't measure it | U32: 3 | V32: no | X32: ≥3 g/day | Y32: A | Z32: One of the best-supported supplements there is for strength and muscle in people who train. There's growing evidence it helps thinking when you're short on sleep. | AA32: yes | AC32: Dose under 2 g: Tier 2 (dose too low). Otherwise Tier 3 with 'strong evidence, keep if you lift'. Never Tier 1: saturation takes weeks, so alternation is invalid. | AD32: dose & form | AE32: Which form, and how much a day? | AF32: monohydrate · HCl · buffered · blend; g a day | AG32: dose under 2 g a day → Tier 2 (dose too low). form = HCl, buffered, or 'creatine blend' → verdict notes monohydrate is the studied form. Otherwise Tier 3 keep. | AI32: Take with water; a small water-weight gain is normal. Fine for kidneys in healthy adults. | AJ32: We can't see this in sleep or HRV, and that's fine, because the evidence here is strong. If you lift, keep it. If you don't, it's mostly doing nothing. | AK32: yes | AL32: 3 g minimum. Look for: ISSN position stand (Kreider 2017).
A33: 32 | B33: protein-powder | C33: Protein powder | D33: buy | E33: supplement | F33: 40 | G33: =F33*12 -> 480 | H33: 1–2 scoops | I33: muscle, satiety | J33: no | M33: slow: builds up or clears over weeks | N33: no experiment | O33: no | R33: not tested | S33: 3 | T33: Can't measure it | U33: 3 | V33: no | X33: no dose rule | Y33: A | Z33: It's food. Useful if you don't get enough protein from meals, irrelevant if you do. | AA33: yes | AC33: Tier 3 (food). Verdict shows cost. | AD33: none | AE33: (no question) | AF33: Routes on the item name alone. | AG33: No flip. | AJ33: This is food, not a supplement, so there's no verdict to give. If it helps you hit protein, keep it. If you already eat enough, it's an expensive way to buy calories. | AK33: no
A34: 33 | B34: bcaas | C34: BCAAs | D34: buy | E34: supplement | F34: 25 | G34: =F34*12 -> 300 | H34: 5–10 g | I34: muscle, recovery | J34: no | M34: slow: builds up or clears over weeks | N34: no experiment | O34: no | R34: not tested | S34: 2 | T34: No test needed | U34: 2 | V34: no | X34: no dose rule | Y34: N | Z34: If you eat enough protein, BCAAs add nothing, and that's been tested several times. They're already in the protein you eat. | AA34: weak | AB34: tested, found nothing | AC34: Tier 2 (tested, found nothing). | AD34: none | AE34: (no question) | AF34: Routes on the item name alone. | AG34: Routes on the item name alone. | AJ34: These are already in every protein source you eat. Trials in people eating enough protein show nothing extra. Easy $25 back. | AK34: yes | AL34: That BCAAs add nothing with adequate protein. Look for: Wolfe 2017 JISSN review.
A35: 34 | B35: glutamine | C35: Glutamine | D35: buy | E35: supplement | F35: 20 | G35: =F35*12 -> 240 | H35: 5 g | I35: gut, recovery | J35: no | M35: slow: builds up or clears over weeks | N35: no experiment | O35: no | R35: not tested | S35: 2 | T35: No test needed | U35: 2 | V35: no | X35: no dose rule | Y35: N | Z35: Found nothing for recovery in healthy adults. The gut evidence is from hospital patients only. | AA35: weak | AB35: tested, found nothing | AC35: Goal gut with a diagnosed condition: Protected. Otherwise Tier 2. | AD35: none | AE35: (no question) | AF35: Routes on the item name alone. | AG35: Routes on the item name alone. | AJ35: Useful in hospitals, not in healthy people. This one can go. | AK35: yes | AL35: No recovery benefit in healthy adults. Look for: Gleeson 2008 review.
A36: 35 | B36: beta-alanine | C36: Beta-alanine | D36: buy | E36: supplement | F36: 20 | G36: =F36*12 -> 240 | H36: 3–6 g | I36: endurance, performance | J36: no | M36: slow: builds up or clears over weeks | N36: no experiment | O36: no | R36: not tested | S36: 3 | T36: Can't measure it | U36: 3 | V36: no | X36: ≥3 g | Y36: A | Z36: Reliably helps with hard efforts lasting 1 to 4 minutes. Does nothing for longer or shorter efforts. The tingling it causes is harmless. | AA36: yes | AC36: Tier 3: keep for rowing / 800 m / CrossFit-type efforts, otherwise verdict says it's not for your training. | AD36: dose & form | AE36: Which form, and how much a day? | AF36: g a day | AG36: dose under 2 g a day → Tier 2 (dose too low). Otherwise Tier 3, with the 1-to-4-minute note. | AJ36: Works, but only for hard efforts of one to four minutes. If that's your sport, keep it. If you run long or lift heavy, it isn't doing anything for you. | AK36: no
A37: 36 | B37: pre-workout | C37: Pre-workout | D37: buy | E37: supplement | F37: 35 | G37: =F37*12 -> 420 | H37: 1 scoop (150–300 mg caffeine) | I37: energy, performance | J37: yes | K37: Time to fall asleep; total sleep | L37: worse if late | M37: fast: acts and clears within hours | N37: 3 days on, 3 days off, for 14 days | O37: yes | P37: 0.9 | Q37: As caffeine after 2pm, if taken after 1pm. | R37: fair | S37: 1 | T37: Tested on you | U37: 1 | V37: yes, if they've been tagging it in Oura or WHOOP | W37: assign (we set the on and off days) | X37: no dose rule | Y37: B | Z37: The caffeine in it works. Most of the other ingredients are in amounts too small to matter. Taken after 2pm, it costs you sleep. | AA37: yes | AC37: Used after 1pm: Tier 1 as caffeine timing. Otherwise Tier 3. | AD37: overlap (automatic) | AE37: (no question) | AF37: Fires on its own when two or more items from the same overlap group are both in the inventory. The person is shown both and asked which one they'd keep. | AG37: Routes on the item name alone. | AH37: caffeine before training | AJ37: If you take this after lunch, it's a caffeine-timing experiment, and one of the most reliable ones we run. | AK37: no
A38: 37 | B38: electrolytes-lmnt-etc | C38: Electrolytes (LMNT etc.) | D38: buy | E38: supplement | F38: 45 | G38: =F38*12 -> 540 | H38: 1 packet daily (~1 g sodium) | I38: hydration, energy, cramps | J38: partial | K38: Resting heart rate; sleep | M38: fast: acts and clears within hours | N38: 3 days on, 3 days off, for 14 days | O38: yes | P38: 0.1 | Q38: No sleep effect to expect. | R38: not tested | S38: 3 | T38: Can't measure it | U38: 3 | V38: no | X38: no dose rule | Y38: C | Z38: Useful if you sweat heavily or eat very low-carb. For a normal day, plain water does the same and the extra sodium isn't helpful. | AA38: weak | AC38: Trains over 1 h/day or keto: Tier 3 keep. Otherwise Tier 3 with 'water does this'. Goal sleep: Tier 1. | AD38: frequency | AE38: How many times in the last 30 days? | AF38: training sessions over an hour, per week | AG38: Training over an hour a day, or keto → Tier 3 keep. Otherwise Tier 3 with 'water does this'. Fires the frequency question for training, not for the product. | AH38: electrolytes | AI38: High blood pressure: a gram of sodium a day on top of diet is not trivial. | AJ38: If you're sweating hard for an hour a day, this earns its place. If you're not, water does the same job, and this is mostly salt and flavour at $45 a month. | AK38: no
A39: 38 | B39: greens-powder-ag1-etc | C39: Greens powder (AG1 etc.) | D39: buy | E39: supplement | F39: 90 | G39: =F39*12 -> 1080 | H39: 1 scoop | I39: general health, energy, gut | J39: no | M39: slow: builds up or clears over weeks | N39: no experiment | O39: no | R39: not tested | S39: 3 | T39: Can't measure it | U39: 3 | V39: no | X39: no dose rule | Y39: D | Z39: There are no independent studies of the product. It's a low-dose multivitamin plus a blend of ingredients whose amounts aren't disclosed. | AA39: weak | AC39: Tier 3 (untestable). Verdict shows annual cost prominently. | AD39: still paying | AE39: Still paying for it? | AF39: Yes · no · not sure. Prefilled from the subscriptions list where the person connected one. | AG39: still paying = yes → Tier 3 with annual cost. Overlap group 'daily multivitamin' → overlap check. | AH39: daily multivitamin | AJ39: We can't measure this one and neither has anyone else; there are no independent trials. What we can show you is that it's over a thousand dollars a year. That's the whole verdict, and the call is yours. | AK39: yes | AL39: No independent trials. Search PubMed for the brand; note funding of anything found.
A40: 39 | B40: collagen-peptides | C40: Collagen peptides | D40: buy | E40: supplement | F40: 35 | G40: =F40*12 -> 420 | H40: 10–15 g | I40: skin, joints, hair | J40: no | M40: slow: builds up or clears over weeks | N40: no experiment | O40: no | R40: not tested | S40: 3 | T40: Can't measure it | U40: 3 | V40: no | X40: ≥10 g/day | Y40: B | Z40: Several trials found small improvements in skin elasticity and joint pain after 8 to 12 weeks at 10 to 15 g a day. Many of those trials were paid for by the companies that sell it. | AA40: yes | AC40: Dose under 5 g: Tier 2 (dose too low). Otherwise Tier 3 with skin/joint rating. | AD40: dose & form | AE40: Which form, and how much a day? | AF40: g a day (a scoop is usually 10 g) | AG40: dose under 5 g a day → Tier 2 (dose too low). 5 to 10 g → Tier 3 with 'below the studied dose'. 10 g or more → Tier 3 with skin/joint rating. | AH40: collagen | AJ40: Invisible to a ring, and the trials that found something used 10 grams for two months. If you want to know, a daily one-tap skin or joint rating over eight weeks is the honest way. | AK40: yes | AL40: 10 to 15 g trials and their funding. Look for: de Miranda 2021 meta-analysis (note sponsor declarations).
A41: 40 | B41: biotin | C41: Biotin | D41: buy | E41: supplement | F41: 8 | G41: =F41*12 -> 96 | H41: 5,000–10,000 mcg | I41: hair, nails | J41: no | M41: slow: builds up or clears over weeks | N41: no experiment | O41: no | R41: not tested | S41: 2 | T41: No test needed | U41: 2 | V41: no | X41: no dose rule | Y41: N | Z41: It only helps if you're deficient, and almost nobody is. It also interferes with common blood tests, including thyroid and heart tests. | AA41: weak | AB41: tested, found nothing | AC41: Tier 2 (tested, found nothing). Safety note always shown. | AD41: none | AE41: (no question) | AF41: Routes on the item name alone. | AG41: Routes on the item name alone. | AI41: Tell your doctor you take it before any blood test; it can distort results. | AJ41: Unless you're deficient, which almost nobody is, this doesn't grow hair. And it can throw off blood tests, which is a real reason to stop, not just a financial one. | AK41: yes | AL41: No hair benefit without deficiency; lab-test interference. Look for: Patel 2017 review; FDA 2017/2019 biotin interference safety communication.
A42: 41 | B42: hyaluronic-acid-oral | C42: Hyaluronic acid (oral) | D42: buy | E42: supplement | F42: 20 | G42: =F42*12 -> 240 | H42: 120–240 mg | I42: skin, joints | J42: no | M42: slow: builds up or clears over weeks | N42: no experiment | O42: no | R42: not tested | S42: 3 | T42: Can't measure it | U42: 3 | V42: no | X42: no dose rule | Y42: C | Z42: Small trials for skin hydration and knee pain. The effects are modest. | AA42: weak | AC42: Tier 3 with rating. | AD42: dose & form | AE42: Which form, and how much a day? | AF42: mg | AG42: dose under 120 mg → Tier 2 (dose too low). Otherwise Tier 3 with skin rating. | AJ42: Can't see it; small trials say maybe. A daily skin rating for eight weeks is the test. | AK42: no
A43: 42 | B43: turmeric-curcumin | C43: Turmeric / curcumin | D43: buy | E43: supplement | F43: 20 | G43: =F43*12 -> 240 | H43: 500–1,000 mg | I43: joints, inflammation | J43: no | M43: slow: builds up or clears over weeks | N43: no experiment | O43: no | R43: not tested | S43: 3 | T43: Can't measure it | U43: 3 | V43: no | X43: formulated versions only (piperine, phytosome) | Y43: B | Z43: Decent trials for knee arthritis pain, but only with forms designed to be absorbed. Plain turmeric powder in a capsule is barely absorbed at all. | AA43: yes | AC43: Plain turmeric powder: Tier 2 (form not absorbed). Formulated curcumin with joint goal: Tier 3 with pain rating. | AD43: dose & form | AE43: Which form, and how much a day? | AF43: plain turmeric · curcumin with piperine · phytosome / Meriva · other; mg | AG43: form = plain turmeric powder or spice capsule → Tier 2 (form not absorbed). form = curcumin with piperine, phytosome, or micellar → Tier 3 with pain rating. | AI43: Blood thinners, gallstones: check. | AJ43: If the label says 'turmeric' without a form designed to be absorbed, almost none of it is absorbed. If it's a proper curcumin, we can't see it in your data but a pain rating can. | AK43: no
A44: 43 | B44: glucosamine-chondroitin | C44: Glucosamine / chondroitin | D44: buy | E44: supplement | F44: 25 | G44: =F44*12 -> 300 | H44: 1,500 mg | I44: joints | J44: no | M44: slow: builds up or clears over weeks | N44: no experiment | O44: no | R44: not tested | S44: 3 | T44: Can't measure it | U44: 3 | V44: no | X44: no dose rule | Y44: C | Z44: The large trials mostly found nothing. People with moderate to severe knee pain may get some relief. | AA44: weak | AC44: Tier 3 with pain rating. | AD44: dose & form | AE44: Which form, and how much a day? | AF44: mg a day | AG44: dose under 1,000 mg a day → Tier 2 (dose too low). Otherwise Tier 3 with pain rating. | AJ44: The big trials were mostly disappointing. If your knees say otherwise, a daily rating will show it. | AK44: no
A45: 44 | B45: coq10 | C45: CoQ10 | D45: buy | E45: supplement | F45: 25 | G45: =F45*12 -> 300 | H45: 100–200 mg | I45: energy, heart | J45: no | M45: slow: builds up or clears over weeks | N45: no experiment | O45: no | R45: not tested | S45: 3 | T45: Can't measure it | U45: 3 | V45: no | X45: no dose rule | Y45: C | Z45: Helps with muscle aches caused by statin drugs, and in some heart conditions. It does nothing for energy in healthy adults. | AA45: weak | AC45: On a statin: Tier 3 keep. Otherwise Tier 3 with 'not for energy in healthy people'. | AD45: none | AE45: (no question) | AF45: Routes on the item name alone. | AG45: Routes on the item name alone. | AJ45: Real use if you're on a statin and achy. As a general energy supplement, the evidence isn't there. | AK45: no
A46: 45 | B46: nmn-nr | C46: NMN / NR | D46: buy | E46: supplement | F46: 70 | G46: =F46*12 -> 840 | H46: 250–1,000 mg | I46: longevity, energy | J46: no | M46: slow: builds up or clears over weeks | N46: no experiment | O46: no | R46: not tested | S46: 3 | T46: Can't measure it | U46: 3 | V46: no | X46: no dose rule | Y46: D | Z46: It raises a molecule called NAD in the blood. No human trial has shown that this changes any health outcome you'd notice. The living-longer data is from mice. | AA46: weak | AC46: Tier 3 (untestable). Annual cost shown. | AD46: none | AE46: (no question) | AF46: Routes on the item name alone. | AG46: No flip. Cost shown. | AJ46: This raises a blood marker; nobody has shown it changes anything you'd notice. We can't test a longevity claim on you, and neither can anyone else. $840 a year, and it's your bet to make. | AK46: yes | AL46: No human outcome trials. Look for: Yoshino 2021 (NMN, no clinical outcome change).
A47: 46 | B47: resveratrol | C47: Resveratrol | D47: buy | E47: supplement | F47: 30 | G47: =F47*12 -> 360 | H47: 250–500 mg | I47: longevity, heart | J47: no | M47: slow: builds up or clears over weeks | N47: no experiment | O47: no | R47: not tested | S47: 2 | T47: No test needed | U47: 2 | V47: no | X47: no dose rule | Y47: N | Z47: Poorly absorbed, and human trials found no benefit for the heart or for blood sugar. | AA47: weak | AB47: tested, found nothing | AC47: Tier 2 (tested, found nothing). | AD47: none | AE47: (no question) | AF47: Routes on the item name alone. | AG47: Routes on the item name alone. | AJ47: The human trials came back flat, and it barely absorbs anyway. This one can go. | AK47: yes | AL47: Human trials found no heart or blood-sugar benefit. Look for: Cochrane review on resveratrol for cardiovascular outcomes; Berman 2017.
A48: 47 | B48: lion-s-mane | C48: Lion's mane | D48: buy | E48: supplement | F48: 30 | G48: =F48*12 -> 360 | H48: 500–1,000 mg | I48: focus, memory | J48: no | M48: slow: builds up or clears over weeks | N48: no experiment | O48: no | R48: not tested | S48: 3 | T48: Can't measure it | U48: 3 | V48: no | X48: no dose rule | Y48: C | Z48: One small trial in older adults with early memory problems. Nothing in healthy adults. | AA48: weak | AC48: Tier 3 with focus rating. | AD48: none | AE48: (no question) | AF48: Routes on the item name alone. | AG48: Routes on the item name alone. | AJ48: The evidence is one small study in a very different group. A daily focus rating for a month is a fairer test than that study. | AK48: no
A49: 48 | B49: rhodiola | C49: Rhodiola | D49: buy | E49: supplement | F49: 20 | G49: =F49*12 -> 240 | H49: 200–400 mg | I49: fatigue, stress | J49: partial | K49: Overnight HRV | M49: slow: builds up or clears over weeks | N49: 2 weeks on, 2 weeks off (not this semester) | O49: no | P49: 0.2 | Q49: Weak trials, slow. | R49: not tested | S49: 3 | T49: Can't measure it | U49: 3 | V49: no | X49: ≥200 mg | Y49: C | Z49: Some trials for tiredness, but they aren't well run. | AA49: weak | AC49: Tier 3 with energy rating. | AD49: dose & form | AE49: Which form, and how much a day? | AF49: mg a day | AG49: dose under 200 mg a day → Tier 2 (dose too low). Otherwise Tier 3 with energy rating. | AJ49: Can't see it in the ring. An energy rating over a few weeks can. | AK49: no
A50: 49 | B50: ginkgo-biloba | C50: Ginkgo biloba | D50: buy | E50: supplement | F50: 15 | G50: =F50*12 -> 180 | H50: 120–240 mg | I50: memory, focus | J50: no | M50: slow: builds up or clears over weeks | N50: no experiment | O50: no | R50: not tested | S50: 2 | T50: No test needed | U50: 2 | V50: no | X50: no dose rule | Y50: N | Z50: Large trials in healthy adults, and trials trying to prevent memory loss, found nothing. | AA50: weak | AB50: tested, found nothing | AC50: Tier 2 (tested, found nothing). | AD50: none | AE50: (no question) | AF50: Routes on the item name alone. | AG50: Routes on the item name alone. | AI50: Blood thinners: interaction. | AJ50: This was tested properly, at scale, and it didn't do anything for memory. One of the clearest 'no' answers in the whole supplement aisle. | AK50: yes | AL50: Large trials found nothing. Look for: GEM study (DeKosky 2008, JAMA); Laws 2012 meta-analysis in healthy adults.
A51: 50 | B51: saffron | C51: Saffron | D51: buy | E51: supplement | F51: 25 | G51: =F51*12 -> 300 | H51: 30 mg | I51: mood | J51: no | M51: slow: builds up or clears over weeks | N51: no experiment | O51: no | R51: not tested | S51: 3 | T51: Can't measure it | U51: 3 | V51: no | X51: ≥30 mg | Y51: B | Z51: Small trials have found, fairly consistently, that it helps with low mood, in some cases about as much as a low dose of antidepressant. | AA51: yes | AC51: Tier 3 with mood rating. Diagnosed depression: Protected. | AD51: dose & form | AE51: Which form, and how much a day? | AF51: mg a day | AG51: dose under 30 mg a day → Tier 2 (dose too low). Otherwise Tier 3 with mood rating. | AJ51: Better evidence than its price tag suggests. We can't see mood in your sleep data, so a daily mood tap is the test. | AK51: yes | AL51: Mood trials. Look for: Lopresti 2014 review.
A52: 51 | B52: phosphatidylserine | C52: Phosphatidylserine | D52: buy | E52: supplement | F52: 30 | G52: =F52*12 -> 360 | H52: 100–300 mg | I52: stress, cortisol, memory | J52: partial | K52: Overnight HRV | M52: slow: builds up or clears over weeks | N52: no experiment | O52: no | P52: 0.1 | Q52: Old, mixed, small. | R52: not tested | S52: 3 | T52: Can't measure it | U52: 3 | V52: no | X52: no dose rule | Y52: C | Z52: A few small, old trials with mixed results. | AA52: weak | AC52: Tier 3. | AD52: none | AE52: (no question) | AF52: Routes on the item name alone. | AG52: Routes on the item name alone. | AJ52: Thin evidence, and we can't see it. Your call on whether $30 a month is worth the maybe. | AK52: no
A53: 52 | B53: zinc-daily | C53: Zinc (daily) | D53: buy | E53: supplement | F53: 8 | G53: =F53*12 -> 96 | H53: 15–50 mg | I53: immunity, testosterone, skin | J53: no | M53: slow: builds up or clears over weeks | N53: no experiment | O53: no | R53: not tested | S53: 2 | T53: No test needed | U53: 2 | V53: no | X53: no dose rule | Y53: C | Z53: Zinc lozenges taken at the first sign of a cold shorten it slightly. Taking zinc every day when you're not low in it does nothing, and more than 40 mg a day drains your copper. | AA53: weak | AB53: tested, found nothing | AC53: Daily use with no deficiency: Tier 2. Lozenges at cold onset: Tier 3 keep. | AD53: dose & form | AE53: Which form, and how much a day? | AF53: mg; daily · lozenges when ill | AG53: dose over 40 mg a day → safety note (copper). Daily use with no deficiency → Tier 2 (tested, found nothing). Lozenges only at cold onset → Tier 3 keep. | AH53: daily multivitamin | AI53: Over 40 mg a day long term causes copper deficiency. | AJ53: Daily zinc without a deficiency doesn't do the things it's sold for, and too much of it causes its own problem. Keep lozenges for the first day of a cold; drop the daily. | AK53: yes | AL53: Copper depletion above 40 mg/day; daily zinc no benefit without deficiency. Look for: NIH ODS zinc fact sheet (tolerable upper limit 40 mg).
A54: 53 | B54: vitamin-c-daily | C54: Vitamin C (daily) | D54: buy | E54: supplement | F54: 8 | G54: =F54*12 -> 96 | H54: 500–1,000 mg | I54: immunity | J54: no | M54: slow: builds up or clears over weeks | N54: no experiment | O54: no | R54: not tested | S54: 3 | T54: Can't measure it | U54: 3 | V54: no | X54: no dose rule | Y54: A | Z54: It doesn't stop you catching colds. It makes them about 8 percent shorter. Cheap and harmless. | AA54: yes | AC54: Tier 3, no push. | AD54: overlap (automatic) | AE54: (no question) | AF54: Fires on its own when two or more items from the same overlap group are both in the inventory. The person is shown both and asked which one they'd keep. | AG54: No flip. | AH54: daily multivitamin | AJ54: Doesn't prevent colds, shortens them by about half a day. It's $8. Not worth an experiment or a fuss either way. | AK54: yes | AL54: 8% figure. Look for: Hemilä 2013, Cochrane.
A55: 54 | B55: elderberry | C55: Elderberry | D55: buy | E55: supplement | F55: 15 | G55: =F55*12 -> 180 | H55: syrup or gummies | I55: immunity | J55: no | M55: slow: builds up or clears over weeks | N55: no experiment | O55: no | R55: not tested | S55: 3 | T55: Can't measure it | U55: 3 | V55: no | X55: no dose rule | Y55: C | Z55: Small trials suggested shorter colds. The biggest and best-run trial found nothing. | AA55: weak | AC55: Tier 3. | AD55: none | AE55: (no question) | AF55: Routes on the item name alone. | AG55: No flip. | AJ55: Evidence is small and the best trial was flat. Can't measure it either way. | AK55: yes | AL55: Largest trial null. Look for: Macknin 2020.
A56: 55 | B56: probiotic-generic-daily | C56: Probiotic (generic daily) | D56: buy | E56: supplement | F56: 30 | G56: =F56*12 -> 360 | H56: daily capsule | I56: gut, immunity, mood | J56: no | M56: slow: builds up or clears over weeks | N56: no experiment | O56: no | R56: not tested | S56: 3 | T56: Can't measure it | U56: 3 | V56: no | X56: strain-specific | Y56: C | Z56: Whether a probiotic helps depends on the exact strain and the exact problem. A generic daily capsule for a healthy gut has little evidence behind it. | AA56: weak | AC56: Tier 3 with gut rating. | AD56: dose & form | AE56: Which form, and how much a day? | AF56: named strain · generic blend · not sure | AG56: form = named strain for a named problem (e.g. Lactobacillus rhamnosus GG for antibiotic diarrhoea) → Tier 3 keep. form = generic blend or 'not sure' → Tier 3 with gut rating. | AJ56: Probiotics are specific tools for specific problems. A generic daily one for general gut health has less behind it than the shelf suggests. A gut rating over a month is the honest test. | AK56: no
A57: 56 | B57: psyllium-fibre | C57: Psyllium / fibre | D57: buy | E57: supplement | F57: 10 | G57: =F57*12 -> 120 | H57: 5–10 g | I57: gut, cholesterol | J57: no | M57: slow: builds up or clears over weeks | N57: no experiment | O57: no | R57: not tested | S57: 3 | T57: Can't measure it | U57: 3 | V57: no | X57: no dose rule | Y57: A | Z57: Well supported for regularity and LDL. | AA57: yes | AC57: Tier 3 keep. | AD57: none | AE57: (no question) | AF57: Routes on the item name alone. | AG57: Routes on the item name alone. | AJ57: Not exciting, and very well proven. Keep. | AK57: no
A58: 57 | B58: digestive-enzymes | C58: Digestive enzymes | D58: buy | E58: supplement | F58: 20 | G58: =F58*12 -> 240 | H58: with meals | I58: bloating, digestion | J58: no | M58: fast: acts and clears within hours | N58: no experiment | O58: no | R58: not tested | S58: 3 | T58: Can't measure it | U58: 3 | V58: no | X58: no dose rule | Y58: D | Z58: No benefit unless a doctor has found you're missing a specific enzyme. The exception is lactase, if dairy upsets your stomach. | AA58: weak | AC58: Lactase for lactose intolerance: Tier 3 keep. Otherwise Tier 3 with 'thin evidence' and gut rating. | AD58: none | AE58: (no question) | AF58: Routes on the item name alone. | AG58: Routes on the item name alone. | AJ58: Unless it's lactase and you're lactose intolerant, there isn't much behind these. A gut rating on and off is a fair test. | AK58: no
A59: 58 | B59: apple-cider-vinegar | C59: Apple cider vinegar | D59: buy | E59: supplement | F59: 10 | G59: =F59*12 -> 120 | H59: 1–2 tbsp daily | I59: weight, glucose, digestion | J59: no | M59: fast: acts and clears within hours | N59: no experiment | O59: no | R59: not tested | S59: 2 | T59: No test needed | U59: 2 | V59: no | X59: no dose rule | Y59: C | Z59: One small trial on weight, and a small effect on blood sugar after meals. It wears away tooth enamel. | AA59: weak | AB59: tested, found nothing | AC59: Goal weight: Tier 2. Goal glucose: Tier 3 (CGM only). | AD59: none | AE59: (no question) | AF59: Routes on the item name alone. | AG59: Routes on the item name alone. | AI59: Dilute it; it damages enamel. | AJ59: For weight, the evidence is one small trial. For your teeth, the evidence is clear. This can go. | AK59: yes | AL59: Weight trial size and enamel erosion. Look for: Khezri 2018 (n=39); dental erosion case reports.
A60: 59 | B60: berberine | C60: Berberine | D60: buy | E60: supplement | F60: 30 | G60: =F60*12 -> 360 | H60: 500 mg, 2–3 times daily | I60: glucose, weight | J60: no | M60: slow: builds up or clears over weeks | N60: no experiment | O60: no | R60: not tested | S60: 3 | T60: Can't measure it | U60: 3 | V60: no | X60: ≥1 g/day | Y60: B | Z60: Lowers blood sugar in people whose blood sugar is high. Calling it 'natural Ozempic' oversells it a lot. It interacts with many medications. | AA60: yes | AC60: Diabetes / prediabetes / on medication: Protected. Otherwise Tier 3. | AD60: dose & form | AE60: Which form, and how much a day? | AF60: mg per dose, doses a day | AG60: dose under 1 g a day → Tier 2 (dose too low). Any medication, diabetes, or prediabetes → Protected. | AI60: Interacts with metformin, statins, blood thinners and more. Ask a clinician. | AJ60: This does something real, which is exactly why it isn't an app decision. If you're on any medication, please run it past whoever prescribes them. | AK60: yes | AL60: Interaction list. Look for: NIH / LiverTox; CYP interactions.
A61: 60 | B61: green-tea-extract-egcg | C61: Green tea extract (EGCG) | D61: buy | E61: supplement | F61: 20 | G61: =F61*12 -> 240 | H61: capsule | I61: fat loss, antioxidant | J61: no | M61: slow: builds up or clears over weeks | N61: no experiment | O61: no | R61: not tested | S61: 2 | T61: No test needed | U61: 2 | V61: no | X61: no dose rule | Y61: C | Z61: A tiny effect on weight. Concentrated extracts have caused liver damage at high doses. | AA61: weak | AB61: tested, found nothing | AC61: Tier 2 with safety note. | AD61: none | AE61: (no question) | AF61: Routes on the item name alone. | AG61: Routes on the item name alone. | AI61: Concentrated extracts have caused liver injury. Tea is fine; capsules are not risk-free. | AJ61: The weight effect is close to zero and the liver risk isn't. Drink the tea instead. | AK61: yes | AL61: Weight effect and liver injury reports. Look for: Cochrane review (Jurgens 2012); Hu 2018 hepatotoxicity review.
A62: 61 | B62: fat-burner-thermogenic | C62: Fat burner / thermogenic | D62: buy | E62: supplement | F62: 40 | G62: =F62*12 -> 480 | H62: daily | I62: weight | J62: yes | K62: Resting heart rate; sleep | L62: worse | M62: fast: acts and clears within hours | N62: 3 days on, 3 days off, for 14 days | O62: yes | P62: 1 | Q62: Resting heart rate up about 3 bpm from the stimulants. A test would show the cost, not a benefit. | R62: not tested | S62: 2 | T62: No test needed | U62: 2 | V62: no | W62: observe only (never assign an on-day) | X62: no dose rule | Y62: N | Z62: Mostly caffeine and other stimulants. They don't burn fat in any amount you'd notice, and they do raise your heart rate and disturb your sleep. | AA62: weak | AB62: tested, found nothing | AC62: Tier 2 (tested, found nothing) with safety note. Optional Tier 1 to show the resting heart rate/sleep cost. | AD62: none | AE62: (no question) | AF62: Routes on the item name alone. | AG62: Routes on the item name alone. | AI62: Stimulant blends raise heart rate and blood pressure. | AJ62: These don't burn fat in any amount you'd notice, and they do raise your resting heart rate. We can show you that number if you want, but the verdict is already in. | AK62: yes | AL62: No fat loss beyond caffeine; heart rate and blood pressure effects. Look for: Jeukendrup & Randell 2011 review.
A63: 62 | B63: testosterone-booster-tribulus-fenugreek-d-aa | C63: Testosterone booster (tribulus, fenugreek, D-AA) | D63: buy | E63: supplement | F63: 40 | G63: =F63*12 -> 480 | H63: daily | I63: testosterone, energy, libido | J63: no | M63: slow: builds up or clears over weeks | N63: no experiment | O63: no | R63: not tested | S63: 2 | T63: No test needed | U63: 2 | V63: no | X63: no dose rule | Y63: N | Z63: Tribulus and D-aspartic acid have been tested and found not to raise testosterone. Fenugreek has a tiny effect on sex drive and none on testosterone. | AA63: weak | AB63: tested, found nothing | AC63: Tier 2. Diagnosed low T: Protected. | AD63: none | AE63: (no question) | AF63: Routes on the item name alone. | AG63: Routes on the item name alone. | AJ63: Tested, repeatedly, and they don't raise testosterone. If you're worried about your levels, that's a blood test and a doctor, not a bottle. | AK63: yes | AL63: Null results for tribulus and D-AA. Look for: Qureshi 2014 tribulus review; Willoughby & Leutholtz 2013 D-AA trial.
A64: 63 | B64: tongkat-ali | C64: Tongkat ali | D64: buy | E64: supplement | F64: 35 | G64: =F64*12 -> 420 | H64: 200–400 mg | I64: testosterone, energy | J64: no | M64: slow: builds up or clears over weeks | N64: no experiment | O64: no | R64: not tested | S64: 3 | T64: Can't measure it | U64: 3 | V64: no | X64: no dose rule | Y64: C | Z64: A few small trials with modest results. Nobody outside the original team has repeated them. | AA64: weak | AC64: Tier 3. | AD64: none | AE64: (no question) | AF64: Routes on the item name alone. | AG64: Routes on the item name alone. | AJ64: Thin, not nothing. We can't see it, so this one is a judgement call with the price in front of you. | AK64: no
A65: 64 | B65: maca | C65: Maca | D65: buy | E65: supplement | F65: 20 | G65: =F65*12 -> 240 | H65: 1.5–3 g | I65: libido, energy | J65: no | M65: slow: builds up or clears over weeks | N65: no experiment | O65: no | R65: not tested | S65: 3 | T65: Can't measure it | U65: 3 | V65: no | X65: no dose rule | Y65: C | Z65: Small trials suggest a little help with sex drive. No change in hormones. | AA65: weak | AC65: Tier 3 with rating. | AD65: none | AE65: (no question) | AF65: Routes on the item name alone. | AG65: Routes on the item name alone. | AJ65: Small evidence for libido, none for hormones. A rating is the only way to know. | AK65: no
A66: 65 | B66: dhea-pregnenolone | C66: DHEA / pregnenolone | D66: buy | E66: supplement | F66: 20 | G66: =F66*12 -> 240 | H66: 25–50 mg | I66: hormones, energy | J66: no | M66: slow: builds up or clears over weeks | N66: no experiment | O66: no | R66: not tested | S66: P | T66: Protected | U66: P | V66: no | X66: no dose rule | Y66: C | Z66: These are hormones. They're not something to experiment with on your own. | AA66: yes | AC66: Always Protected. | AD66: none | AE66: (no question) | AF66: Routes on the item name alone. | AG66: Routes on the item name alone. | AI66: Hormone precursors: prescriber only. | AJ66: This is a hormone. We don't route hormones, and we'd gently suggest a doctor does. | AK66: no
A67: 66 | B67: taurine | C67: Taurine | D67: buy | E67: supplement | F67: 12 | G67: =F67*12 -> 144 | H67: 1–3 g | I67: energy, longevity | J67: no | M67: slow: builds up or clears over weeks | N67: no experiment | O67: no | R67: not tested | S67: 3 | T67: Can't measure it | U67: 3 | V67: no | X67: no dose rule | Y67: D | Z67: The longevity claim is from a 2023 mouse study. Human outcome data doesn't exist. | AA67: weak | AC67: Tier 3. | AD67: none | AE67: (no question) | AF67: Routes on the item name alone. | AG67: Routes on the item name alone. | AJ67: The headline study was in mice. There's nothing to see in your data and nothing yet in humans. At $12 it isn't costing you much, but it isn't doing much either. | AK67: no
A68: 67 | B68: activated-charcoal | C68: Activated charcoal | D68: buy | E68: supplement | F68: 12 | G68: =F68*12 -> 144 | H68: capsules | I68: detox, bloating | J68: no | M68: fast: acts and clears within hours | N68: no experiment | O68: no | R68: not tested | S68: 2 | T68: No test needed | U68: 2 | V68: no | X68: no dose rule | Y68: N | Z68: There's no 'detox' for it to do. It soaks up whatever is in your gut, including your medications and vitamins. | AA68: no | AB68: no way it could work | AC68: Tier 2 with safety note. | AD68: none | AE68: (no question) | AF68: Routes on the item name alone. | AG68: Routes on the item name alone. | AI68: Binds medications, including the pill. Don't take near any medication. | AJ68: There's nothing for it to detox, and it will absorb your medications and vitamins along with everything else. This one can go. | AK68: yes | AL68: No detox mechanism; binds medications. Look for: any toxicology text; NHS / FDA guidance on charcoal and drug absorption.
A69: 68 | B69: sea-moss | C69: Sea moss | D69: buy | E69: supplement | F69: 20 | G69: =F69*12 -> 240 | H69: gel or capsule | I69: immunity, thyroid, skin | J69: no | M69: slow: builds up or clears over weeks | N69: no experiment | O69: no | R69: not tested | S69: 2 | T69: No test needed | U69: 2 | V69: no | X69: no dose rule | Y69: D | Z69: No human trials. The amount of iodine in it varies wildly and can be far too much. | AA69: weak | AB69: no way it could work | AC69: Tier 2 with safety note. | AD69: none | AE69: (no question) | AF69: Routes on the item name alone. | AG69: Routes on the item name alone. | AI69: Iodine excess can disturb thyroid function. | AJ69: No trials, unpredictable iodine, and the claims come from social media. Yours to keep, but we'd rather you knew. | AK69: yes | AL69: No human trials; iodine variability. Look for: iodine content analyses of seaweed products; NIH iodine upper limit.
A70: 69 | B70: shilajit | C70: Shilajit | D70: buy | E70: supplement | F70: 30 | G70: =F70*12 -> 360 | H70: capsule or resin | I70: energy, testosterone | J70: no | M70: slow: builds up or clears over weeks | N70: no experiment | O70: no | R70: not tested | S70: 3 | T70: Can't measure it | U70: 3 | V70: no | X70: no dose rule | Y70: D | Z70: One small trial paid for by the seller. Raw shilajit has repeatedly been found to contain lead and arsenic. | AA70: weak | AC70: Tier 3 with safety note. | AD70: none | AE70: (no question) | AF70: Routes on the item name alone. | AG70: Routes on the item name alone. | AI70: Buy only tested products; raw shilajit has contained lead and arsenic. | AJ70: Can't see it, thin evidence, and the safety note matters more than the verdict. | AK70: no
A71: 70 | B71: chlorophyll-water | C71: Chlorophyll water | D71: buy | E71: supplement | F71: 15 | G71: =F71*12 -> 180 | H71: daily | I71: skin, detox, odour | J71: no | M71: slow: builds up or clears over weeks | N71: no experiment | O71: no | R71: not tested | S71: 2 | T71: No test needed | U71: 2 | V71: no | X71: no dose rule | Y71: D | Z71: TikTok origin. No trials. | AA71: no | AB71: no way it could work | AC71: Tier 2. | AD71: none | AE71: (no question) | AF71: Routes on the item name alone. | AG71: Routes on the item name alone. | AJ71: There are no studies of this at all. The claims came from social media, and there's nothing here for us to test. Yours to keep, but we'd rather you knew. | AK71: yes | AL71: No human trials for the skin / detox claims.
A72: 71 | B72: colostrum | C72: Colostrum | D72: buy | E72: supplement | F72: 50 | G72: =F72*12 -> 600 | H72: daily | I72: gut, immunity | J72: no | M72: slow: builds up or clears over weeks | N72: no experiment | O72: no | R72: not tested | S72: 3 | T72: Can't measure it | U72: 3 | V72: no | X72: no dose rule | Y72: C | Z72: Some evidence it helps endurance athletes with gut problems during hard training. The general wellness claims haven't been tested. | AA72: weak | AC72: Tier 3 with gut rating; annual cost shown. | AD72: none | AE72: (no question) | AF72: Routes on the item name alone. | AG72: Routes on the item name alone. | AJ72: Some evidence in endurance athletes, none for the general claims. $600 a year for a maybe. Your call. | AK72: no
A73: 72 | B73: mushroom-coffee | C73: Mushroom coffee | D73: buy | E73: food/drink | F73: 35 | G73: =F73*12 -> 420 | H73: daily | I73: focus, energy, fewer jitters | J73: yes | K73: Time to fall asleep (as caffeine) | M73: fast: acts and clears within hours | N73: 3 days on, 3 days off, for 14 days | O73: yes | P73: 0.4 | Q73: About a third of normal coffee's caffeine. | R73: not tested | S73: 3 | T73: Can't measure it | U73: 3 | V73: yes, if they've been tagging it in Oura or WHOOP | X73: no dose rule | Y73: D | Z73: The mushroom part has no human evidence at these doses. It's coffee with less caffeine. | AA73: weak | AC73: Tier 3 for the mushroom claim. Tier 1 as caffeine timing if after 1pm. | AD73: overlap (automatic) | AE73: (no question) | AF73: Fires on its own when two or more items from the same overlap group are both in the inventory. The person is shown both and asked which one they'd keep. | AG73: Routes on the item name alone. | AH73: caffeine before training | AJ73: The mushrooms aren't doing anything we or anyone else can measure. The 'fewer jitters' is just less caffeine. A smaller cup of ordinary coffee gets you the same thing for a lot less. | AK73: no
A74: 73 | B74: nootropic-stack-alpha-gpc-etc | C74: Nootropic stack (alpha-GPC etc.) | D74: buy | E74: supplement | F74: 60 | G74: =F74*12 -> 720 | H74: daily | I74: focus | J74: no | M74: fast: acts and clears within hours | N74: no experiment | O74: no | R74: not tested | S74: 3 | T74: Can't measure it | U74: 3 | V74: no | X74: no dose rule | Y74: C | Z74: Taken one ingredient at a time, the evidence is small. Nobody has tested the stacks as products. | AA74: weak | AC74: Tier 3 with focus rating. Contains caffeine after 1pm: Tier 1. | AD74: none | AE74: (no question) | AF74: Routes on the item name alone. | AG74: Routes on the item name alone. | AJ74: A focus rating on and off is the only honest test. Two weeks, one tap a day. | AK74: no
A75: 74 | B75: inositol | C75: Inositol | D75: buy | E75: supplement | F75: 20 | G75: =F75*12 -> 240 | H75: 2–4 g | I75: PCOS, mood, sleep | J75: no | M75: slow: builds up or clears over weeks | N75: no experiment | O75: no | R75: not tested | S75: P | T75: Protected | U75: P | V75: no | X75: no dose rule | Y75: B | Z75: Decent evidence for PCOS. That's a medical use. | AA75: yes | AC75: PCOS: Protected. Otherwise Tier 3. | AD75: none | AE75: (no question) | AF75: Routes on the item name alone. | AG75: Routes on the item name alone. | AJ75: If this is for PCOS, it's between you and your clinician, and we stay out of it. | AK75: no
A76: 75 | B76: vitamin-k2 | C76: Vitamin K2 | D76: buy | E76: supplement | F76: 15 | G76: =F76*12 -> 180 | H76: 100–200 mcg | I76: bone, heart | J76: no | M76: slow: builds up or clears over weeks | N76: no experiment | O76: no | R76: not tested | S76: 3 | T76: Can't measure it | U76: 3 | V76: no | X76: no dose rule | Y76: C | Z76: Makes sense biologically. The trials that measured actual health outcomes are small and mixed. | AA76: weak | AC76: Tier 3. | AD76: overlap (automatic) | AE76: (no question) | AF76: Fires on its own when two or more items from the same overlap group are both in the inventory. The person is shown both and asked which one they'd keep. | AG76: Routes on the item name alone. | AH76: daily multivitamin | AI76: Warfarin: do not take without prescriber. | AJ76: Plausible, unproven, invisible to us. Keep it if the logic convinces you; the trials haven't settled it. | AK76: no
A77: 76 | B77: calcium | C77: Calcium | D77: buy | E77: supplement | F77: 8 | G77: =F77*12 -> 96 | H77: 500–1,000 mg | I77: bone | J77: no | M77: slow: builds up or clears over weeks | N77: no experiment | O77: no | R77: not tested | S77: 3 | T77: Can't measure it | U77: 3 | V77: no | X77: no dose rule | Y77: B | Z77: Useful if you don't get much from food. Taking more than you need may slightly raise heart risk. | AA77: yes | AC77: Doctor-sourced: Protected. Otherwise Tier 3 with 'food first'. | AD77: none | AE77: (no question) | AF77: Routes on the item name alone. | AG77: Routes on the item name alone. | AJ77: Food first for this one. If a doctor asked you to take it, keep taking it. | AK77: no
A78: 77 | B78: evening-primrose-oil | C78: Evening primrose oil | D78: buy | E78: supplement | F78: 12 | G78: =F78*12 -> 144 | H78: 1–2 g | I78: PMS, skin | J78: no | M78: slow: builds up or clears over weeks | N78: no experiment | O78: no | R78: not tested | S78: 2 | T78: No test needed | U78: 2 | V78: no | X78: no dose rule | Y78: N | Z78: Careful reviews of all the trials found it works no better than a sugar pill for PMS or eczema. | AA78: weak | AB78: tested, found nothing | AC78: Tier 2. | AD78: none | AE78: (no question) | AF78: Routes on the item name alone. | AG78: Routes on the item name alone. | AJ78: Reviewed properly and it didn't beat placebo. This can go. | AK78: yes | AL78: No better than placebo for PMS or eczema. Look for: Cochrane review (Bamford 2013) for eczema; Whelan 2009 for PMS.
A79: 78 | B79: coffee-after-2pm | C79: Coffee after 2pm | D79: do | E79: timing | F79: 0 | G79: =F79*12 -> 0 | H79: 1 cup | I79: energy, focus | J79: yes | K79: Total sleep; time to fall asleep; deep sleep | L79: worse | M79: fast: acts and clears within hours | N79: 3 days on, 3 days off, for 14 days | O79: yes | P79: 1 | Q79: About 41 min less total sleep in the classic trial, against a typical 45-min swing. Bigger for people who drink a lot; smaller for fast caffeine metabolisers. | R79: fair | S79: 1 | T79: Tested on you | U79: 1 | V79: yes, if they've been tagging it in Oura or WHOOP | W79: assign (we set the on and off days) | X79: no dose rule | Y79: A | Z79: In the classic trial, 400 mg of caffeine taken six hours before bed cut sleep by about 41 minutes, and people didn't notice. Caffeine takes 5 to 6 hours for half of it to clear, and that varies a lot from person to person. | AA79: yes | AC79: Tier 1. Best first experiment for most users. | AD79: clock time | AE79: What time, usually? | AF79: before noon · 12 to 2pm · 2 to 5pm · after 5pm. Prefilled from Oura or WHOOP caffeine tags where present. | AG79: last coffee before noon → not a hypothesis; Tier 3 'not an issue for you'. 12 to 2pm → Tier 1 with a smaller expected effect (0.6, so gated to Tier 3 unless they choose to run it). After 2pm → Tier 1. | AH79: caffeine before training | AJ79: The single most reliable experiment we run, and the one most people are wrong about in one direction or the other. Fourteen days and you'll have your own number. | AK79: yes | AL79: The 41-minute figure and 6-hour timing. Look for: Drake 2013, J Clin Sleep Med.
A80: 79 | B80: second-or-third-coffee | C80: Second (or third) coffee | D80: do | E80: timing | F80: 0 | G80: =F80*12 -> 0 | I80: energy | J80: yes | K80: Total sleep; overnight HRV | M80: fast: acts and clears within hours | N80: 3 days on, 3 days off, for 14 days | O80: yes | P80: 0.4 | Q80: Each extra cup after the first adds a modest, inconsistent amount. Only clear when the second cup is late. | R80: low | S80: 1 | T80: Tested on you | U80: 3, effect too small | V80: yes, if they've been tagging it in Oura or WHOOP | W80: assign (we set the on and off days) | X80: no dose rule | Y80: B | Z80: Total daily caffeine above about 400 mg is where sleep and HRV effects become consistent. | AA80: yes | AC80: Tier 1: on = usual, off = cap at one. | AD80: frequency | AE80: How many times in the last 30 days? | AF80: cups a day: 1 · 2 · 3 · 4+ | AG80: cups a day = 1 → not a hypothesis. 2 → Tier 3 (effect too small). 3 or more → Tier 1 (expected effect 0.8). | AH80: caffeine before training | AJ80: The second cup usually makes a smaller difference than the timing of the last one. That's about two fifths of one night's normal swing, so a two-week test would very likely come back inconclusive. We'll show you what the trials found and what it costs, and if you'd still like to run it, you can, knowing that going in. | AK80: no
A81: 80 | B81: energy-drinks | C81: Energy drinks | D81: buy | E81: food/drink | F81: 60 | G81: =F81*12 -> 720 | H81: 1 can | I81: energy | J81: yes | K81: Total sleep; resting heart rate | L81: worse | M81: fast: acts and clears within hours | N81: 3 days on, 3 days off, for 14 days | O81: yes | P81: 0.7 | Q81: Caffeine effect plus a small resting-heart-rate rise from sugar and taurine. Clearer if drunk after 2pm; use 1.0 then. | R81: low | S81: 1 | T81: Tested on you | U81: 3, effect too small | V81: yes, if they've been tagging it in Oura or WHOOP | W81: observe only (never assign an on-day) | X81: no dose rule | Y81: B | Z81: Caffeine plus sugar. Same sleep cost as coffee with more effect on resting heart rate. | AA81: yes | AC81: Tier 1. | AD81: clock time | AE81: What time, usually? | AF81: before noon · 12 to 2pm · after 2pm | AG81: after 2pm → Tier 1 (effect 1.0). Before 2pm → Tier 3 (effect too small). Observe-only either way. | AH81: caffeine before training | AJ81: Unless you drink these late in the day, the effect on a single night is modest. That's about two thirds of one night's normal swing, so a two-week test would very likely come back inconclusive. We'll show you what the trials found and what it costs, and if you'd still like to run it, you can, knowing that going in. | AK81: no
A82: 81 | B82: decaf-swap-after-noon | C82: Decaf swap after noon | D82: do | E82: timing | F82: 0 | G82: =F82*12 -> 0 | I82: sleep | J82: yes | K82: Time to fall asleep; total sleep | L82: better | M82: fast: acts and clears within hours | N82: 3 days on, 3 days off, for 14 days | O82: yes | P82: 1 | Q82: The caffeine experiment in reverse. Same size as 'coffee after 2pm'. | R82: fair | S82: 1 | T82: Tested on you | U82: 1 | V82: yes, if they've been tagging it in Oura or WHOOP | W82: assign (we set the on and off days) | X82: no dose rule | Y82: A | Z82: The inverse of the caffeine experiment. Keeps the ritual, drops the drug. | AA82: yes | AC82: Tier 1. | AD82: none | AE82: (no question) | AF82: Routes on the item name alone. | AG82: Offered as the 'off' condition for the coffee experiment; not routed on its own. | AJ82: Keeps the cup, drops the caffeine. A clean test of whether it was ever the caffeine. | AK82: no
A83: 82 | B83: matcha-green-tea-in-the-afternoon | C83: Matcha / green tea in the afternoon | D83: do | E83: timing | F83: 0 | G83: =F83*12 -> 0 | I83: focus, calm | J83: yes | K83: Time to fall asleep | M83: fast: acts and clears within hours | N83: 3 days on, 3 days off, for 14 days | O83: yes | P83: 0.4 | Q83: About a third of the caffeine of coffee, so about a third of the effect. | R83: low | S83: 1 | T83: Tested on you | U83: 3, effect too small | V83: yes, if they've been tagging it in Oura or WHOOP | W83: assign (we set the on and off days) | X83: no dose rule | Y83: B | Z83: Less caffeine than coffee, plus theanine. Still caffeine. | AA83: yes | AC83: Tier 1 if after 2pm. | AD83: clock time | AE83: What time, usually? | AF83: before 2pm · after 2pm | AG83: after 2pm → Tier 3 (effect too small, can run anyway). Before → not a hypothesis. | AH83: caffeine before training | AJ83: There's about a third as much caffeine here as in coffee. That's about two fifths of one night's normal swing, so a two-week test would very likely come back inconclusive. We'll show you what the trials found and what it costs, and if you'd still like to run it, you can, knowing that going in. | AK83: no
A84: 83 | B84: alcohol-in-the-evening | C84: Alcohol in the evening | D84: do | E84: food/drink | F84: 80 | G84: =F84*12 -> 960 | H84: 1–2 drinks | I84: relaxation, social | J84: yes | K84: Overnight HRV; resting heart rate; REM; time awake during the night | L84: worse | M84: fast: acts and clears within hours | N84: 3 days on, 3 days off, for 14 days | O84: yes | P84: 1.5 | Q84: HRV down 10 to 25% and resting heart rate up 3 to 5 bpm on every wearable's own data. The largest, most reliable effect in the whole table. | R84: good | S84: 1 | T84: Tested on you | U84: 1 | V84: partly: the night has a recognisable pattern we can flag for them to confirm | W84: observe only (never assign an on-day) | X84: no dose rule | Y84: A | Z84: Even one or two drinks lower overnight HRV (the recovery number) by 10 to 25 percent and raise resting heart rate by a few beats. You fall asleep faster and then sleep worse in the second half of the night. It shows up the same night on every wearable. | AA84: yes | AC84: Tier 1. Frame as 'what does a drink cost you', never as 'stop drinking'. | AD84: nights a week | AE84: How many nights a week, usually? | AF84: 0 · 1 to 2 · 3 to 4 · 5 or more | AG84: 0 → not in the inventory. 1 to 2 → Tier 1, observe-only, expected effect 1.5 but fewer on-nights, so the test runs over 3 to 4 weeks. 3 or more → Tier 1, observe-only, two weeks is enough. | AI84: If drinking feels hard to change, that's a conversation for a person, not an app. | AJ84: We're not going to tell you not to drink. We're going to show you what one drink costs you the next morning, in your own numbers, and let you decide what it's worth on a Tuesday. | AK84: yes | AL84: HRV 10 to 25% and resting heart rate 3 to 5 bpm figures. Look for: WHOOP and Oura published member data; Pietilä 2018 (Firstbeat).
A85: 84 | B85: late-dinner-within-2-3-h-of-bed | C85: Late dinner (within 2–3 h of bed) | D85: do | E85: timing | F85: 0 | G85: =F85*12 -> 0 | I85: sleep, digestion | J85: yes | K85: Time to fall asleep; time awake during the night; resting heart rate | L85: worse | M85: fast: acts and clears within hours | N85: 3 days on, 3 days off, for 14 days | O85: yes | P85: 0.5 | Q85: Resting heart rate up 1 to 2 bpm overnight; sleep changes are small. Bigger for heavy meals; use 0.8 if the person eats their main meal within 90 min of bed. | R85: low | S85: 1 | T85: Tested on you | U85: 3, effect too small | V85: yes, if they've been tagging it in Oura or WHOOP | W85: assign (we set the on and off days) | X85: no dose rule | Y85: B | Z85: Eating close to bedtime raises your heart rate and body temperature overnight. The effect on sleep is modest and varies a lot between people. | AA85: yes | AC85: Tier 1. | AD85: clock time | AE85: What time, usually? | AF85: hours between dinner and bed: under 1.5 · 1.5 to 3 · over 3 | AG85: main meal within 90 min of bed → expected effect 0.8, Tier 1. 90 min to 3 h → Tier 3 (effect too small). Over 3 h → not a hypothesis. | AJ85: Eating late nudges your overnight heart rate up a little. That's about half of one night's normal swing, so a two-week test would very likely come back inconclusive. We'll show you what the trials found and what it costs, and if you'd still like to run it, you can, knowing that going in. | AK85: no
A86: 85 | B86: big-carbohydrate-dinner | C86: Big carbohydrate dinner | D86: do | E86: timing | F86: 0 | G86: =F86*12 -> 0 | I86: sleep | J86: yes | K86: Time to fall asleep | L86: better? | M86: fast: acts and clears within hours | N86: 3 days on, 3 days off, for 14 days | O86: yes | P86: 0.4 | Q86: One small trial, about 5 min faster to fall asleep. | R86: low | S86: 1 | T86: Tested on you | U86: 3, effect too small | V86: yes, if they've been tagging it in Oura or WHOOP | W86: assign (we set the on and off days) | X86: no dose rule | Y86: C | Z86: In one small trial, a high-carb meal about 4 hours before bed helped people fall asleep faster. Sugar right before bed does the opposite. | AA86: yes | AC86: Tier 1. | AD86: none | AE86: (no question) | AF86: Routes on the item name alone. | AG86: Routes on the item name alone. | AJ86: One small trial found a few minutes' difference. That's about two fifths of one night's normal swing, so a two-week test would very likely come back inconclusive. We'll show you what the trials found and what it costs, and if you'd still like to run it, you can, knowing that going in. | AK86: no
A87: 86 | B87: dessert-sugar-before-bed | C87: Dessert / sugar before bed | D87: do | E87: timing | F87: 0 | G87: =F87*12 -> 0 | J87: yes | K87: Time awake during the night; deep sleep | L87: worse | M87: fast: acts and clears within hours | N87: 3 days on, 3 days off, for 14 days | O87: yes | P87: 0.3 | Q87: Lighter sleep in studies that watched people; no controlled trial. | R87: low | S87: 1 | T87: Tested on you | U87: 3, effect too small | V87: yes, if they've been tagging it in Oura or WHOOP | W87: assign (we set the on and off days) | X87: no dose rule | Y87: C | Z87: Associated with lighter sleep in studies that watched people rather than tested them. | AA87: yes | AC87: Tier 1. | AD87: none | AE87: (no question) | AF87: Routes on the item name alone. | AG87: Routes on the item name alone. | AJ87: The studies here only watched people; nobody has run a proper test. That's about a third of one night's normal swing, so a two-week test would very likely come back inconclusive. We'll show you what the trials found and what it costs, and if you'd still like to run it, you can, knowing that going in. | AK87: no
A88: 87 | B88: fasting-window-skipping-breakfast | C88: Fasting window / skipping breakfast | D88: do | E88: timing | F88: 0 | G88: =F88*12 -> 0 | H88: 16:8 | I88: weight, energy, focus | J88: partial | K88: Resting heart rate; sleep | M88: slow: builds up or clears over weeks | N88: 2 weeks on, 2 weeks off (not this semester) | O88: no | P88: 0.4 | Q88: Small, mixed effects on sleep and resting heart rate. Slow to settle, so long blocks only. | R88: not in two weeks | S88: 1 | T88: Tested on you | U88: 1, queued (slow) | V88: yes, if they've been tagging it in Oura or WHOOP | W88: assign (we set the on and off days) | X88: no dose rule | Y88: B | Z88: For weight, it works about as well as any other way of eating less. Its effects on sleep and HRV are small and vary between people. Your body takes about a week to adjust, so 3-day blocks are too short to test it fairly. | AA88: yes | AC88: Slow: long blocks only. v1: evidence line. | AD88: none | AE88: (no question) | AF88: Routes on the item name alone. | AG88: Routes on the item name alone. | AI88: Not for anyone with a history of disordered eating. | AJ88: This changes your body over a week, not a night, so we can't test it fairly in three-day blocks yet. What we can tell you: for weight it works about as well as any other way of eating less. | AK88: no
A89: 88 | B89: fluids-after-8pm | C89: Fluids after 8pm | D89: do | E89: timing | F89: 0 | G89: =F89*12 -> 0 | J89: yes | K89: Time awake during the night | L89: worse | M89: fast: acts and clears within hours | N89: 3 days on, 3 days off, for 14 days | O89: yes | P89: 0.6 | Q89: About 8 fewer minutes awake for people who wake to use the bathroom; near zero for people who don't. Use 1.0 if the person reports night bathroom trips. | R89: low | S89: 1 | T89: Tested on you | U89: 3, effect too small | V89: yes, if they've been tagging it in Oura or WHOOP | W89: assign (we set the on and off days) | X89: no dose rule | Y89: B | Z89: Needing the bathroom is the most common reason people wake in the middle of the night. Cutting fluids after 8pm reduces it. | AA89: yes | AC89: Tier 1. | AD89: frequency | AE89: How many times in the last 30 days? | AF89: bathroom wake-ups a week: 0 · 1 to 2 · 3+ | AG89: wakes for the bathroom most nights → expected effect 1.0, Tier 1. Rarely → Tier 3 (effect too small). | AJ89: If you don't wake up needing the bathroom, this one probably isn't costing you anything. That's about three fifths of one night's normal swing, so a two-week test would very likely come back inconclusive. We'll show you what the trials found and what it costs, and if you'd still like to run it, you can, knowing that going in. | AK89: yes | AL89: Nocturia as the top cause of waking. Look for: any urology review of nocturia prevalence.
A90: 89 | B90: nicotine-pouches-vape | C90: Nicotine pouches / vape | D90: buy | E90: food/drink | F90: 60 | G90: =F90*12 -> 720 | H90: several a day | I90: focus, stress | J90: yes | K90: Time to fall asleep; overnight HRV; resting heart rate | L90: worse | M90: fast: acts and clears within hours | N90: 3 days on, 3 days off, for 14 days | O90: yes | P90: 0.9 | Q90: Stimulant: resting heart rate up, HRV down, on nights with evening use. Similar in size to late caffeine. | R90: fair | S90: 1 | T90: Tested on you | U90: 1 | V90: yes, if they've been tagging it in Oura or WHOOP | W90: observe only (never assign an on-day) | X90: no dose rule | Y90: A | Z90: Nicotine is a stimulant. It raises resting heart rate, lowers HRV (the recovery number), and breaks up sleep. Using it in the evening is the worst for sleep. | AA90: yes | AC90: Tier 1: test evening use only (on = as usual, off = none after 6pm). Never frame as a quit programme. | AD90: clock time | AE90: What time, usually? | AF90: daytime only · some after 6pm · mostly evening | AG90: any use after 6pm → Tier 1 (evening timing test, observe-only). Daytime only → Tier 3 (not a sleep hypothesis). | AI90: Dependence is real and quitting is hard. We test evening timing, not abstinence. | AJ90: We won't lecture you. We'll test just the evening ones and show you what they cost your sleep. What you do with that is yours. | AK90: yes | AL90: Nicotine and sleep. Look for: Jaehne 2009 review.
A91: 90 | B91: kombucha-probiotic-drinks | C91: Kombucha / probiotic drinks | D91: buy | E91: food/drink | F91: 40 | G91: =F91*12 -> 480 | H91: daily | I91: gut | J91: no | M91: slow: builds up or clears over weeks | N91: no experiment | O91: no | R91: not tested | S91: 3 | T91: Can't measure it | U91: 3 | V91: no | X91: no dose rule | Y91: D | Z91: It has hardly been tested as a health drink at all. | AA91: weak | AC91: Tier 3 with gut rating; cost shown. | AD91: none | AE91: (no question) | AF91: Routes on the item name alone. | AG91: Routes on the item name alone. | AJ91: Untested, and $40 a month. A gut rating on and off is the only test that exists. | AK91: no
A92: 91 | B92: bone-broth | C92: Bone broth | D92: buy | E92: food/drink | F92: 40 | G92: =F92*12 -> 480 | H92: daily | I92: gut, skin, joints | J92: no | M92: slow: builds up or clears over weeks | N92: no experiment | O92: no | R92: not tested | S92: 3 | T92: Can't measure it | U92: 3 | V92: no | X92: no dose rule | Y92: D | Z92: A modest protein source. The collagen claims don't survive digestion any better than collagen powder. | AA92: weak | AC92: Tier 3. | AD92: overlap (automatic) | AE92: (no question) | AF92: Fires on its own when two or more items from the same overlap group are both in the inventory. The person is shown both and asked which one they'd keep. | AG92: Routes on the item name alone. | AH92: collagen | AJ92: This is a decent bowl of soup with some protein in it. The claims about skin and joints aren't backed by studies, but you don't need a verdict to enjoy soup. If it's $40 a month, that's the only thing worth looking at. | AK92: no
A93: 92 | B93: training-after-7pm | C93: Training after 7pm | D93: do | E93: timing | F93: 0 | G93: =F93*12 -> 0 | I93: fitness, sleep | J93: yes | K93: Time to fall asleep; total sleep; overnight HRV | M93: fast: acts and clears within hours | N93: 3 days on, 3 days off, for 14 days | O93: yes | P93: 0.8 | Q93: Averages near zero, but for hard sessions ending within 2 h of bed, time to fall asleep and resting heart rate move by about a full swing. Use 1.0 if the session is vigorous and late; 0.4 if it's easy or ends before 8pm. | R93: fair | S93: 1 | T93: Tested on you | U93: 1 | V93: yes, the wearable already records it | W93: assign (we set the on and off days) | X93: no dose rule | Y93: B | Z93: Reviews that pool many studies say evening exercise doesn't harm sleep on average, but vigorous exercise within an hour of bed delays it. Individual variation is large. | AA93: yes | AC93: Tier 1. On = usual late session, off = same session before 7pm or in the morning. | AD93: clock time | AE93: What time, usually? | AF93: (read from workouts) | AG93: Read from the wearable's workout times; not asked. Vigorous session ending within 2 h of bed on 3+ nights a week → expected effect 1.0, Tier 1. Easy sessions, or ending before 8pm → Tier 3 (effect too small). | AJ93: On average, evening training is fine for sleep. But you're not an average, and this is one of the things that varies most from person to person. Worth a real test. | AK93: yes | AL93: Averages versus late-vigorous subgroup. Look for: Stutz 2019 meta-analysis, Sports Med.
A94: 93 | B94: morning-workout-before-8am | C94: Morning workout before 8am | D94: do | E94: timing | F94: 0 | G94: =F94*12 -> 0 | I94: energy, sleep | J94: yes | K94: Time to fall asleep; deep sleep | L94: better | M94: fast: acts and clears within hours | N94: 3 days on, 3 days off, for 14 days | O94: yes | P94: 0.3 | Q94: Small body-clock nudge over days. | R94: low | S94: 1 | T94: Tested on you | U94: 3, effect too small | V94: yes, the wearable already records it | W94: assign (we set the on and off days) | X94: no dose rule | Y94: B | Z94: Exercising in the morning nudges your body clock a little earlier. | AA94: yes | AC94: Tier 1. | AD94: none | AE94: (no question) | AF94: Routes on the item name alone. | AG94: Routes on the item name alone. | AJ94: The body-clock nudge from morning exercise is real but small night to night. That's about a third of one night's normal swing, so a two-week test would very likely come back inconclusive. We'll show you what the trials found and what it costs, and if you'd still like to run it, you can, knowing that going in. | AK94: no
A95: 94 | B95: hiit-in-the-evening | C95: HIIT in the evening | D95: do | E95: timing | F95: 0 | G95: =F95*12 -> 0 | I95: fitness | J95: yes | K95: Time to fall asleep; overnight HRV; resting heart rate | L95: worse | M95: fast: acts and clears within hours | N95: 3 days on, 3 days off, for 14 days | O95: yes | P95: 1 | Q95: Resting heart rate and body temperature stay up into the night after hard intervals close to bed. | R95: fair | S95: 1 | T95: Tested on you | U95: 1 | V95: yes, the wearable already records it | W95: assign (we set the on and off days) | X95: no dose rule | Y95: B | Z95: Vigorous intervals within 1–2 hours of bed raise body temperature and resting heart rate into the night. | AA95: yes | AC95: Tier 1. | AD95: clock time | AE95: What time, usually? | AF95: (read from workouts) | AG95: Read from workouts. Within 2 h of bed → Tier 1. Otherwise not a hypothesis. | AJ95: Of all the training-timing questions, this is the one most likely to show up in your sleep data. Worth the two weeks. | AK95: no
A96: 95 | B96: 10-000-steps-daily-walk | C96: 10,000 steps / daily walk | D96: do | E96: habit | F96: 0 | G96: =F96*12 -> 0 | I96: fitness, sleep, mood | J96: yes | K96: Resting heart rate; share of time in bed actually asleep | L96: better | M96: fast: acts and clears within hours | N96: 3 days on, 3 days off, for 14 days | O96: yes | P96: 0.5 | Q96: Resting heart rate 1 bpm lower and sleep a little more solid on active days. Real but small night to night. | R96: low | S96: 1 | T96: Tested on you | U96: 3, effect too small | V96: yes, the wearable already records it | W96: assign (we set the on and off days) | X96: no dose rule | Y96: A | Z96: Being active during the day reliably improves sleep and lowers resting heart rate over time. The effect of any single day's walk on that night's sleep is real but modest. | AA96: yes | AC96: Tier 1 (on = 8k+, off = under 5k). Verdict notes long-term benefits regardless of the night-level result. | AD96: none | AE96: (no question) | AF96: Routes on the item name alone. | AG96: Routes on the item name alone. | AJ96: Walking pays off over months; one day's effect on that night is small. That's about half of one night's normal swing, so a two-week test would very likely come back inconclusive. We'll show you what the trials found and what it costs, and if you'd still like to run it, you can, knowing that going in. | AK96: no
A97: 96 | B97: zone-2-cardio-3-h-week | C97: Zone 2 cardio (3+ h/week) | D97: do | E97: habit | F97: 0 | G97: =F97*12 -> 0 | I97: fitness, HRV, longevity | J97: yes | K97: Resting heart rate; HRV (trend) | L97: better | M97: slow: builds up or clears over weeks | N97: 2 weeks on, 2 weeks off (not this semester) | O97: no | P97: 1 | Q97: Over 8 to 12 weeks, HRV and resting heart rate move by a full swing or more. Too slow for 3-day blocks. | R97: not in two weeks | S97: 1 | T97: Tested on you | U97: 1, queued (slow) | V97: yes, the wearable already records it | W97: assign (we set the on and off days) | X97: no dose rule | Y97: A | Z97: Raises HRV (the recovery number) and lowers resting heart rate over 6 to 12 weeks. The evidence is strong. It's far too slow to test in 3-day blocks. | AA97: yes | AC97: Long-block only. v1: evidence line plus trend view. | AD97: none | AE97: (no question) | AF97: Routes on the item name alone. | AG97: Routes on the item name alone. | AJ97: Works, slowly, and the evidence is about as strong as it gets. Not a two-week test; we'll show you the trend instead. | AK97: yes | AL97: HRV and RHR change over weeks. Look for: Sandercock 2005 meta-analysis.
A98: 97 | B98: strength-training | C98: Strength training | D98: do | E98: habit | F98: 0 | G98: =F98*12 -> 0 | I98: strength, body composition | J98: yes | K98: Resting heart rate; HRV (trend) | L98: better | M98: slow: builds up or clears over weeks | N98: 2 weeks on, 2 weeks off (not this semester) | O98: no | R98: not tested | S98: 3 | T98: Can't measure it | U98: 3 | V98: yes, the wearable already records it | X98: no dose rule | Y98: A | Z98: Strong evidence for almost everything you could want. It's not something that changes a single night's sleep, so it isn't a candidate for a two-week test. | AA98: yes | AC98: Not routed for testing. Verdict: keep. | AD98: none | AE98: (no question) | AF98: Routes on the item name alone. | AG98: Routes on the item name alone. | AJ98: Not something we'd ever suggest testing away. Keep. | AK98: no
A99: 98 | B99: stretching-yoga-before-bed | C99: Stretching / yoga before bed | D99: do | E99: habit | F99: 0 | G99: =F99*12 -> 0 | I99: sleep, recovery | J99: yes | K99: Time to fall asleep; overnight HRV | L99: better | M99: fast: acts and clears within hours | N99: 3 days on, 3 days off, for 14 days | O99: yes | P99: 0.4 | Q99: About 5 min faster to fall asleep in small trials. | R99: low | S99: 1 | T99: Tested on you | U99: 3, effect too small | V99: yes, if they've been tagging it in Oura or WHOOP | W99: assign (we set the on and off days) | X99: no dose rule | Y99: C | Z99: Small trials found gentle evening yoga helped people fall asleep faster. | AA99: yes | AC99: Tier 1. | AD99: none | AE99: (no question) | AF99: Routes on the item name alone. | AG99: Routes on the item name alone. | AJ99: The small trials found a few minutes' difference in falling asleep. That's about two fifths of one night's normal swing, so a two-week test would very likely come back inconclusive. We'll show you what the trials found and what it costs, and if you'd still like to run it, you can, knowing that going in. | AK99: no
A100: 99 | B100: cold-plunge-ice-bath | C100: Cold plunge / ice bath | D100: buy | E100: device | F100: 100 | G100: =F100*12 -> 1200 | H100: 3–5 min | I100: recovery, mood, HRV, resilience | J100: yes | K100: Overnight HRV; resting heart rate; time to fall asleep (if evening) | M100: fast: acts and clears within hours | N100: 3 days on, 3 days off, for 14 days | O100: yes | P100: 0.5 | Q100: Acute HRV changes are real but go both ways; evening plunges can delay sleep. Direction is the interesting part, so a test is still worth it if the person is choosing whether to buy one. | R100: low | S100: 1 | T100: Tested on you | U100: 3, effect too small | V100: yes, if they've been tagging it in Oura or WHOOP | W100: assign (we set the on and off days) | X100: no dose rule | Y100: C | Z100: It does change HRV and alertness in the short term. The recovery benefits are modest, and doing it right after lifting weights actually reduces muscle growth. An evening plunge can make it harder to fall asleep. | AA100: yes | AC100: Tier 1. Pre-purchase proxy: cold shower for 14 days. | AD100: clock time | AE100: What time, usually? | AF100: morning · evening | AG100: evening → number = time to fall asleep. Morning → number = overnight HRV. Either way Tier 3 (effect too small, can run anyway); pre-purchase proxy offered. | AI100: Cold shock is a real cardiac stressor. Ease in, never alone. | AJ100: The overnight effect is small and goes both ways from person to person. That's about half of one night's normal swing, so a two-week test would very likely come back inconclusive. We'll show you what the trials found and what it costs, and if you'd still like to run it, you can, knowing that going in. | AK100: yes | AL100: Blunted muscle growth after lifting. Look for: Roberts 2015, J Physiol.
...

Sheet Experiment Priority
A1: What the engine can actually test this semester, biggest expected effect first
A2: Only rows that pass every gate: a wearable can see it, it acts within hours, expected effect at least 0.8, and it can run without long blocks. This is the real Tier 1 list.
A4: Item | B4: Expected effect | C4: Chance of a clear answer | D4: Number we'd watch | E4: On-days | F4: Read from history? | G4: Why this size
A5: Alcohol in the evening | B5: 1.5 | C5: good | D5: Overnight HRV; resting heart rate; REM; time awake during the night | E5: observe only | F5: partly: the night has a recognisable pattern we can flag for them to confirm | G5: HRV down 10 to 25% and resting heart rate up 3 to 5 bpm on every wearable's own data. The largest, most reliable effect in the whole table.
A6: Coffee after 2pm | B6: 1 | C6: fair | D6: Total sleep; time to fall asleep; deep sleep | E6: assign | F6: yes, if they've been tagging it in Oura or WHOOP | G6: About 41 min less total sleep in the classic trial, against a typical 45-min swing. Bigger for people who drink a lot; smaller for fast caffeine metabolisers.
A7: Decaf swap after noon | B7: 1 | C7: fair | D7: Time to fall asleep; total sleep | E7: assign | F7: yes, if they've been tagging it in Oura or WHOOP | G7: The caffeine experiment in reverse. Same size as 'coffee after 2pm'.
A8: HIIT in the evening | B8: 1 | C8: fair | D8: Time to fall asleep; overnight HRV; resting heart rate | E8: assign | F8: yes, the wearable already records it | G8: Resting heart rate and body temperature stay up into the night after hard intervals close to bed.
A9: Hot bath / shower 1–2 h before bed | B9: 1 | C9: fair | D9: Time to fall asleep | E9: assign | F9: yes, if they've been tagging it in Oura or WHOOP | G9: About 10 min faster to fall asleep in a review of 17 studies, against a 10-min swing.
A10: Pre-workout | B10: 0.9 | C10: fair | D10: Time to fall asleep; total sleep | E10: assign | F10: yes, if they've been tagging it in Oura or WHOOP | G10: As caffeine after 2pm, if taken after 1pm.
A11: Nicotine pouches / vape | B11: 0.9 | C11: fair | D11: Time to fall asleep; overnight HRV; resting heart rate | E11: observe only | F11: yes, if they've been tagging it in Oura or WHOOP | G11: Stimulant: resting heart rate up, HRV down, on nights with evening use. Similar in size to late caffeine.
A12: Sauna (post-workout or evening) | B12: 0.9 | C12: fair | D12: Overnight HRV; resting heart rate; time to fall asleep | E12: assign | F12: yes, if they've been tagging it in Oura or WHOOP | G12: Falling asleep about 10 min faster after an evening session, against a 10-min swing.
A13: Journaling / worry list before bed | B13: 0.9 | C13: fair | D13: Time to fall asleep | E13: assign | F13: yes, if they've been tagging it in Oura or WHOOP | G13: About 9 min faster to fall asleep in the lab trial, against a 10-min swing.
A14: Screens / phone in bed | B14: 0.9 | C14: fair | D14: Time to fall asleep; total sleep | E14: assign | F14: yes, if they've been tagging it in Oura or WHOOP | G14: 20 to 30 min later to fall asleep with social media in bed, against a 10-min swing on time to fall asleep and a 45-min swing on total sleep. Bigger for heavy users.
A15: Consistent wake time (±30 min) | B15: 0.9 | C15: fair | D15: Share of time in bed actually asleep; time to fall asleep | E15: assign | F15: yes, the wearable already records it | G15: Share of time asleep up 3 to 5 points and easier to fall asleep once the clock settles. Builds over the first week.
A16: Sauna / bathhouse membership | B16: 0.9 | C16: fair | D16: Overnight HRV; time to fall asleep | E16: assign | F16: yes, if they've been tagging it in Oura or WHOOP | G16: Same as sauna.
... A20: Afternoon nap (after 3pm or over 30 min) | B20: 0.8 | C20: fair | D20: Time to fall asleep; total night sleep | E20: assign | F20: yes, the wearable already records it | G20: 10 to 15 min longer to fall asleep on nap days for people who nap late. Near zero for short early naps.
A22: How to read this
A23: Offer experiments from the top of this list first. If the person's own 'thing I'd most like permission to drop' is further down, run it second, not first, so the guarantee has its best shot in the first 60 days.
A24: 'Observe only' rows (alcohol, nicotine, energy drinks) never get an assigned on-day. The app waits for the person to have a drink, records it, and compares those nights with the rest. Off-days can still be suggested: 'try three nights without.'
A25: Rows marked 'yes, the wearable already records it' can be shown as a day-one hypothesis from the person's own history before any test starts: 'On the 22 nights in the last six months when you trained after 7pm, you slept 34 minutes less.' That's the reveal the landing page promises, and it needs no new data.
A27: Queued for a longer test (slow items, not this semester) | B27: Expected effect over weeks | C27: Why
A28: Ashwagandha (KSM-66 / Sensoril) | B28: 0.5 | C28: Modest sleep and HRV changes after 6 to 8 weeks. Long blocks only.
A29: THC / cannabis for sleep | B29: 1.2 | C29: 15 min faster to fall asleep and a clear REM drop, but the catch-up effect on stopping breaks the 3/3 test. Special design only.
A30: Fasting window / skipping breakfast | B30: 0.4 | C30: Small, mixed effects on sleep and resting heart rate. Slow to settle, so long blocks only.
A31: Zone 2 cardio (3+ h/week) | B31: 1 | C31: Over 8 to 12 weeks, HRV and resting heart rate move by a full swing or more. Too slow for 3-day blocks.
A33: A wearable could see it, but the effect is too small for two weeks (gets Tier 3 treatment, can run anyway) | B33: Expected effect | C33: Why
A34: Energy drinks | B34: 0.7 | C34: Caffeine effect plus a small resting-heart-rate rise from sugar and taurine. Clearer if drunk after 2pm; use 1.0 then.
A35: Weekend sleep-in (over 1 h) | B35: 0.7 | C35: Sunday night 20 to 40 min later to fall asleep, but it's one night a week, which dilutes the average. Use weekly blocks.
A36: Smart lights (warm, dim in the evening) | B36: 0.7 | C36: About 8 min earlier to fall asleep when evening light is dimmed.
A37: Bedroom temperature (thermostat) | B37: 0.7 | C37: A 2°C change moves deep sleep and time awake by about two-thirds of a swing for the average person. Use 1.0 if the room is over 21°C or the person wakes hot.
A38: Separate bedrooms some nights | B38: 0.7 | C38: About 10 fewer minutes awake apart; varies a lot.
A39: Sleep gummies (blend) | B39: 0.6 | C39: The melatonin in it, usually at a higher-than-useful dose.
A40: Fluids after 8pm | B40: 0.6 | C40: About 8 fewer minutes awake for people who wake to use the bathroom; near zero for people who don't. Use 1.0 if the person reports night bathroom trips.
A41: Earplugs | B41: 0.6 | C41: About 8 fewer minutes awake in a noisy room; near zero in a quiet one. Use 1.0 for a loud street or a snoring partner.
A42: Blackout / light leak | B42: 0.6 | C42: Resting heart rate about 1 bpm lower and a few fewer minutes awake with real darkness.
A43: Late dinner (within 2–3 h of bed) | B43: 0.5 | C43: Resting heart rate up 1 to 2 bpm overnight; sleep changes are small. Bigger for heavy meals; use 0.8 if the person eats their main meal within 90 min of bed.
A44: 10,000 steps / daily walk | B44: 0.5 | C44: Resting heart rate 1 bpm lower and sleep a little more solid on active days. Real but small night to night.
A45: Cold plunge / ice bath | B45: 0.5 | C45: Acute HRV changes are real but go both ways; evening plunges can delay sleep. Direction is the interesting part, so a test is still worth it if the person is choosing whether to buy one.
... A94: Humidifier | B94: 0.1 | C94: No trials; a comfort item.

Sheet Goal to Number
A1: What the person says it's for, and which number the test is judged on
A3: Goal the person picks | B3: Number the test watches | C3: Notes | D3: Daily rating instead?
A4: sleep (general) | B4: Total sleep | C4: Unless the row names a more specific number, total sleep is the default. It's the most reliable across devices. | D4: no
A5: falling asleep | B5: Time to fall asleep | C5: For anything taken or done in the hour before bed. | D5: no
A6: staying asleep / waking at night | B6: Time awake during the night | C6: Fluids, noise, light, pets, partners. | D6: no
A7: deep sleep | B7: Deep sleep | C7: Treat consumer sleep-stage numbers as a rough guide. | D7: no
A8: recovery / stress / HRV | B8: Overnight HRV | C8: The most sensitive number to alcohol and stress. Compare in proportion to the person's average. | D8: no
A9: energy | B9: Resting heart rate plus total sleep | C9: A wearable can't see energy directly. If the person means 'how I feel', use the daily rating instead. | D9: yes
A10: fitness | B10: Resting heart rate (trend over weeks) | C10: Long blocks only. | D10: no
A11: focus / memory | B11: (none) | C11: Not visible to a wearable. Daily one-tap rating. | D11: yes
A12: mood / anxiety | B12: (none) | C12: Not visible. Daily one-tap rating. Diagnosed condition means Protected. | D12: yes
A13: skin / hair | B13: (none) | C13: Not visible. Daily one-tap rating over 8 weeks. | D13: yes
A14: gut / bloating | B14: (none) | C14: Not visible. Daily one-tap rating over 4 weeks. | D14: yes
... A19: testosterone / hormones | B19: (none) | C19: A blood test and a clinician. Never routed. | D19: no

Sheet Glossary
A1: Glossary: every technical word in this file, in plain English
A3: Word | B3: What it means
A4: HRV (heart rate variability) | B4: The tiny changes in timing between one heartbeat and the next. Higher usually means rested and recovering well; lower means under strain. It's the number that drops the morning after drinks. In user-facing text we call it 'the recovery number'.
A5: Resting heart rate | B5: Heart rate while asleep. Lower is generally better. Very steady night to night, so small changes stand out.
A6: Deep sleep | B6: The stage where the body does most physical repair. Mostly the first half of the night.
A7: REM sleep | B7: The dreaming stage. Alcohol and cannabis cut it down; stopping them causes a few nights of extra REM (the 'catch-up' effect).
A8: Time to fall asleep | B8: Minutes from lights-out to asleep. Wearables estimate it; Oura and WHOOP do it better than Apple or Garmin.
A9: Time awake during the night | B9: Minutes awake after first falling asleep.
A10: Share of time in bed actually asleep | B10: Asleep minutes divided by minutes in bed. Above about 85% is normal.
A11: Normal night-to-night swing | B11: How much a number bounces around from one night to the next for one person with nothing changed. Also called the standard deviation. Every verdict compares the change we saw to this swing.
A12: Expected effect (in units of the swing) | B12: How big the change is likely to be, divided by the swing. 1.0 = 'about as big as a normal bad night versus a normal good night'. Under 0.8, a two-week test usually can't tell the effect apart from noise.
A13: Inconclusive | B13: The change was inside the person's normal swing, so we can't tell whether it did anything. A real answer, not a failed test.
A14: 3 days on, 3 days off | B14: The standard test. Same person compared with themselves, so most of life's noise cancels out.
... A25: Wellness versus health | B25: Wellness = sleep, recovery, energy, habits; goals the person sets, data the person owns. Health = diagnosing, treating, preventing conditions. We only ever do the first one.

Sheet Numbers we can watch
A1: Number | B1: Unit | C1: What it tells you | D1: Oura | E1: WHOOP | F1: Apple Watch | G1: Garmin / Fitbit | H1: Normal night-to-night swing for one person | I1: Change we could reliably spot in a 2-week test | J1: What usually moves it | K1: Things to know
A2: Total sleep | B2: min | C2: How long you were asleep in total | D2: yes | E2: yes | F2: yes | G2: yes | H2: about 45 min | I2: about 55 to 70 min | J2: Caffeine timing, alcohol, late fluids, a regular wake time, screens | K2: The most reliable number across devices. Default for any 'sleep' goal unless the row names another.
A3: Time to fall asleep | B3: min | C3: Minutes from lights-out to asleep | D3: yes | E3: yes | F3: estimated | G3: estimated | H3: about 10 min | I3: about 12 to 16 min | J3: Hot bath, melatonin, caffeine, screens, evening exercise, a worry list | K3: Devices guess when lights went out, so this is noisier on Apple and Garmin. Ignore nights over 60 minutes as one-offs.
A4: Deep sleep | B4: min | C4: Physical-repair sleep | D4: yes | E4: yes | F4: yes | G4: yes | H4: about 15 min | I4: about 18 to 24 min | J4: Alcohol (less, late in the night), room temperature, exercise | K4: Consumer sleep-stage numbers agree with a lab sleep study only about 60 to 70% of the time. A rough guide.
A5: REM sleep | B5: min | C5: Dreaming sleep | D5: yes | E5: yes | F5: yes | G5: yes | H5: about 15 min | I5: about 18 to 24 min | J5: Alcohol (less), cannabis (less), late caffeine (less) | K5: Same rough-guide warning. Stopping alcohol or cannabis causes extra REM for a few nights, which confuses on/off tests.
A6: Time awake during the night | B6: min | C6: Minutes awake after first falling asleep | D6: yes | E6: yes | F6: yes | G6: yes | H6: about 12 min | I6: about 15 to 19 min | J6: Fluids after 8pm, alcohol, noise, light, pets, partner, kids | K6: Leave out any night marked 'kids woke me'.
A7: Share of time in bed asleep | B7: % | C7: Asleep minutes divided by minutes in bed | D7: yes | E7: yes | F7: yes | G7: yes | H7: about 4 points | I7: about 5 to 6 points | J7: A regular wake time, blackout, earplugs, temperature | K7: Can't go above 100, so little room to improve above about 92%.
A8: Overnight HRV | B8: ms | C8: The recovery number: how rested and unstrained your body is | D8: yes | E8: yes | F8: spot checks only | G8: yes | H8: about 12 ms (about 20% of the person's average) | I8: about 15 to 19 ms | J8: Alcohol (down 10 to 25%), late training, illness, slow breathing (up), sauna | K8: Most sensitive to alcohol and stress. The swing grows with the average, so compare in proportion. Apple Watch only samples now and then.
A9: Resting heart rate | B9: bpm | C9: Heart rate while asleep | D9: yes | E9: yes | F9: yes | G9: yes | H9: about 2.5 bpm | I9: about 3 to 4 bpm | J9: Alcohol (up), late meal (up), illness, stimulants, fitness (down over weeks) | K9: Very steady, so small changes stand out. Shifts 1 to 2 bpm across the menstrual cycle; note cycle phase where the person opts in.
A10: Breathing rate | B10: breaths/min | C10: Breaths per minute asleep | D10: yes | E10: yes | F10: yes | G10: some | H10: about 0.5 | I10: about 0.6 to 0.8 | J10: Illness, alcohol, nasal strips, air quality | K10: Mostly an early-illness flag.
A11: Skin temperature | B11: °C from your usual | C11: How far tonight is from your own normal | D11: yes | E11: yes (4.0 and later) | F11: yes (Series 8 and later) | G11: some | H11: about 0.25 | I11: about 0.3 | J11: Alcohol, late meal, illness, room temperature, cycle phase | K11: Part of the alcohol 'signature' the app can spot. Leave out of tests where the cycle would confuse it.
A12: Steps / activity | B12: count | C12: How much you moved today | D12: yes | E12: yes | F12: yes | G12: yes | H12: not used as an outcome | I12: not used as an outcome | J12: An input, not a result | K12: Defines 'on' days for walking tests; flags days that shouldn't count.
A13: Workouts (with start time) | B13: list | C13: When and how hard you trained | D13: yes | E13: yes | F13: yes | G13: yes | H13: not used as an outcome | I13: not used as an outcome | J13: An input, not a result | K13: This is how 'training after 7pm' can be read from history with no tagging at all.
A15: How 'measurable' is decided, in plain words (what the guarantee rests on)
A16: First week: the app watches, to learn the person's normal. From that week plus all 'off' days it works out each number's normal night-to-night swing for that person.
A17: The test: two weeks of 3 on, 3 off. On-nights versus off-nights (usually 7 against 7; fewer if taps were missed, and a missed tap is 'unknown', never 'failed'). One question: is the difference bigger than this person's normal swing by enough that it would only happen by chance about 1 time in 20, in the direction we said before the start? Yes = kept or dropped. No = inconclusive. The number is shown either way.
A18: In practice: with 7 nights a side, the difference needs to be about one and a half times the swing to count reliably. That is why the Items sheet carries an expected-effect column and why rows under 0.8 are not sent to a two-week test by default. Alcohol on HRV and afternoon caffeine on total sleep are one to two swings, so they usually resolve. Magnesium on deep sleep is a fifth to a third of a swing, so it would almost always come back inconclusive, and the person is told that on day one instead.
A19: Nights that shouldn't count: the person can flag a night (ill, travelling, a child woke them, an unusually hard session) and it's left out. Weekend nights are spread evenly by starting the schedule on a Monday.
A20: Reading history first: for items the wearable already records (workouts, wake times, naps) or that the person has been tagging, the app can compare past on-nights and off-nights before any test. Treat that as a hypothesis, not a verdict: those nights weren't randomised, so other things differed too. The test confirms it.
A22: Where the data comes from this semester
A23: Oura and WHOOP: connect with one tap and get their history, including tags and workouts. Apple Health needs an iPhone app, which the team can't build this semester. So version 1 is Oura or WHOOP, or typing in the nightly numbers by hand.

Sheet Verdict Templates
A1: Which verdict | B1: Template (words in braces get filled in) | C1: Example, filled in
A2: Tier 1, kept | B2: {item}: {number} was {change} better on the days you did it, against your normal swing of {swing}. That's real, and it's yours. Kept. | C2: Morning walk: your overnight HRV was 6 points higher on the days you walked, against your normal swing of 3. That's real, and it's yours. Kept.
A3: Tier 1, dropped | B3: {item}: {number} was {change} worse on the days you did it, outside your normal swing of {swing}. {months} months in{source_clause}. Dropped, and {cost} a month back. | C3: Training after 7pm: your total sleep was 41 minutes shorter on the nights you trained late, outside your normal swing of 30. Fourteen months in, and you'd never had a way to check. Dropped.
A4: Tier 1, inconclusive | B4: {item}: {change} on {number}, inside your normal swing of {swing}. At this dose, your body didn't show a change we could detect. That's a real answer, not a failed one. Your call whether it stays. It costs {cost} a month. | C4: Melatonin: 3 minutes faster to fall asleep, inside your normal swing of 10. At this dose, your body didn't show a change we could detect. That's a real answer, not a failed one. Your call whether it stays. It costs $10 a month.
A5: Tier 1, day-one hypothesis from history | B5: {item}: on the {n_on} nights in the last {months} months when you {did it}, {number} was {change} {better/worse} than the other {n_off} nights. That's a pattern, not proof yet; other things differed on those nights too. Want to test it properly? | C5: Training after 7pm: on the 22 nights in the last six months when you trained late, your total sleep was 34 minutes shorter than the other 140 nights. That's a pattern, not proof yet; other things differed on those nights too. Want to test it properly?
A6: Tier 1, observe-only (morning after) | B6: Last night: {what}. {number} came in {change} under your usual, and you were awake {awake} minutes more than normal. That's one {what}-night logged. {remaining} to go. | C6: Last night: two drinks. Your HRV came in 19 points under your usual, and you were awake 34 minutes more than normal. That's one drinking night logged. Twelve to go.
A7: Tier 1, slow (can't run yet) | B7: {item}: this works over weeks, not nights, so a two-week on/off test would be unfair to it. What the trials found: {evidence}. We've put it in the queue for a longer test. | C7: Ashwagandha: this works over weeks, not nights, so a two-week on/off test would be unfair to it. What the trials found: people said they felt less stressed after 6 to 8 weeks. We've put it in the queue for a longer test.
A8: Tier 3, effect too small to see (new in v3) | B8: {hook} Even when it works, the studies found a change of about {fraction} of one night's normal swing, so a two-week test would very likely come back inconclusive. We'll show you what the trials found and what it costs. If you'd still like to run the test, you can, knowing that going in. | C8: Magnesium glycinate: even in the studies where it worked, the change was a few minutes, mostly in people who were low in magnesium. Even when it works, the studies found a change of about a third of one night's normal swing, so a two-week test would very likely come back inconclusive. We'll show you what the trials found and what it costs. If you'd still like to run the test, you can, knowing that going in.
A9: Tier 2, dose too low | B9: {item}: the amount you're taking ({dose}) is below what the studies used ({threshold}). Nothing about you is the problem; the amount is. {cost} a month back, or step up to the studied amount and we'll test it properly. | C9: Krill oil: the amount you're taking (500 mg) is below what the studies used (1 g of EPA and DHA). Nothing about you is the problem; the amount is. $30 a month back, or step up to the studied amount and we'll test it properly.
A10: Tier 2, form not absorbed | B10: {item}: this version ({form}) isn't absorbed well enough to do what you bought it for. Same ingredient, different version, and it becomes testable. {cost} a month back either way. | C10: Magnesium oxide: this version isn't absorbed well enough to do what you bought it for. Same ingredient as glycinate, and that one can be tested. $8 a month back either way.
A11: Tier 2, tested and found nothing | B11: {item}: this has been tested properly, more than once, and it didn't do what it's sold for. You did the reasonable thing with the information you had. {months} months in{source_clause}. {cost} a month back. | C11: Ginkgo: this has been tested properly, more than once, and it didn't do what it's sold for. You did the reasonable thing with the information you had. Two years in, on a friend's word. $15 a month back.
A12: Tier 2, no way it could work | B12: {item}: there's no known way for this to do what it claims, and no study says otherwise. If it's part of a routine you like, keep the routine. The {cost} is the only thing on trial. | C12: Salt lamp: there's no known way for this to do what it claims, and no study says otherwise. It's a nice lamp. Keep the lamp.
... A19: The 'where it came from' clause | B19: influencer: ', from something you saw online' | friend: ', on a friend's word' | podcast: ', after a podcast' | ad: ', from an ad' | don't remember: ', and you don't remember why, which is its own kind of answer' | doctor: never reached, it's Protected | C19: Rule: the source is context, never a punchline. Say it once, in the past tense, and move on.

Sheet Tone Guide
A1: Tone Guide: how a verdict is allowed to sound
A2: Every rule here is backed by a finding on the Emotional Positioning sheet. If a rule and a sentence disagree, the sentence changes.
A4: Name the effort before the number | B4: 'Eight months, every night' comes before the verdict. The verdict is about the item, never about their discipline.
A5: The source is context, not a punchline | B5: 'Started from a reel' is said once, in the past tense, and the sentence moves on. Never 'you fell for'.
A6: Tier 3 is never 'drop' | B6: 'We can't see it, here's the cost, here's the evidence, your call.' Several Tier 3 verdicts say keep.
A7: Tier 2 is about the dose or the study, never the person | B7: 'The amount is the problem, not you.' They acted sensibly on what they knew. Say so when it's true.
A8: Show the number, never the word 'wasted' | B8: Money appears as a plain figure and a plain 'back'.
A9: Free and enjoyed means keep | B9: If it costs nothing, does no harm, and they like it, the verdict says keep, whatever the number.
A10: Protected gets one sentence and no opinion | B10: Acknowledged and left alone. No evidence summary, no cost framing, no nudge.
A11: Safety notes are short, plain, and point to a person | B11: 'Ask a clinician.' One sentence, no alarm, then stop.
A12: Inconclusive gets its own respect | B12: 'Your body didn't show a change we could detect at this dose. That's a real answer.'
A13: Too-small-to-see gets told up front | B13: When the likely effect is under the gate, say so on day one, and let them run it anyway if they want. Never set up a test that's built to fail and then call the result inconclusive.
A14: Report what happened, not what they are | B14: 'Your HRV was 18 points lower after the drinks' is about the night. 'Your recovery is poor' is about the person. Always the first kind.
A15: Every off-plan night gets a normal next morning | B15: No red, no 'strain' warnings, no 'you should'. The number is shown, the cause is named, the day moves on.
... A22: Words we do use | B22: your call, yours, back (as in '$22 a month back'), kept, dropped, inconclusive, a real answer, we can't see it, what the studies found, your normal swing, your number, the night, the day, worth it, knowing that going in

Sheet Emotional Positioning
A1: Emotional positioning: what the psychology research says, and what we do about it
A2: Full sources in Emotional-Positioning-Research.md next to this file.
A4: The problem, stated plainly
A5: Every wearable app today is built on the same assumption: show people a bad number and they'll behave better. The research says the opposite happens more often than not. A bad number that points at the person makes them feel judged, and people who feel judged argue with the app, hide from it, or do the thing more. The ring goes in the drawer. That gap is psychological, not technical, and it's the positioning.
A7: Six findings, and what each one changes in the product
A8: 1. Feedback that points at the self makes performance worse | B8: Kluger and DeNisi (1996) pooled 607 studies and found over a third of feedback made people perform worse. Feedback aimed at the person ('your recovery is poor') hurts; feedback kept on the task ('sleep was 41 minutes shorter on those nights') helps. WHAT WE DO: every verdict is about the night and the habit, never the person. No score that describes you.
A9: 2. One slip plus guilt leads to a bigger slip | B9: The 'what-the-hell effect' (Polivy and Herman): once someone feels they've blown it, they abandon the whole plan. In drinkers, the guiltiest about last night drank MORE the next night (UCL, 2025). WHAT WE DO: the morning after an off-plan night is a normal morning. The number is shown, the cause named without comment, nothing is red, the experiment continues.
A10: 3. Being told what to do makes ambivalent people argue back | B10: Motivational interviewing's 'righting reflex': push one side and the person defends the other. Directive styles produce more drop-out. Health-app experiments find controlling language raises resistance and choice lowers it. WHAT WE DO: no 'should', ever. Every verdict ends with the decision in their hands. That now includes the gated rows: 'run it anyway' is offered, not withheld.
A11: 4. Self-compassion predicts healthier behaviour, not laziness | B11: Sirois, Kitner and Hirsch (2015), 15 samples, 3,252 people: people kinder to themselves after failing do MORE healthy things, because they aren't spending energy on shame. WHAT WE DO: lapses are expected. Missed taps are unknown, never failed. A reset protocol for bad weeks.
A12: 5. Praise the process, not the person, and the same for criticism | B12: Dweck: 'you worked hard' builds persistence, 'you're smart' makes people fragile. WHAT WE DO: 'Eight months, every night' comes before every verdict.
A13: 6. The tracker itself can become the problem | B13: Baron et al. (2017) named orthosomnia: people at sleep clinics with normal sleep and real anxiety from chasing a score. Epstein's work found apps punish lapses instead of designing for them. WHAT WE DO: no daily score, no dashboard, one line a day, verdicts every two weeks, an option to hide the wearable's own score.
A15: The morning after drinks: side by side
A16: What they get now | B16: A red recovery of 31%. A strain warning. 'Alcohol had a significant negative impact.' A suggestion to take it easy. The person feels flamed for a nice evening, and has learned nothing they didn't know.
A17: What we show, if alcohol is the current experiment | B17: 'Last night: two drinks. Your HRV came in 19 points under your usual, and you were awake 34 minutes more than normal. That's one drinking night logged. Twelve to go.' Nothing else. No colour. (This is an observe-only item: the app never assigned that night. It recognised the pattern and asked them to confirm.)
A18: What we show, if it isn't the current experiment | B18: Nothing about it. If the night looks unusual, one optional tap: 'Anything different last night?' so it can be kept out of the running test.
A19: What the verdict says two weeks later | B19: 'Alcohol: HRV was 17 points lower and you slept 38 minutes less on drinking nights, against your normal swing of 9 points and 30 minutes. That's the size of it. Now you know what a Tuesday drink costs and what a Saturday one is worth. Yours to spend.'
A20: Why this is positioning, not just copy | B20: Every other product casts itself as the coach and the user as the one being corrected. This one casts the user as the person deciding and itself as the friend who checked the numbers. 'Editing, not deprivation' is the brand, and the morning-after screen is where it's proven.
A22: Eight rules for every screen
A23: Describe the night, not the person | B23: Numbers about what happened. Never a score about who they are.
A24: Nothing is ever red | B24: Kept, dropped and inconclusive are words in the same type.
A25: Name the cause, skip the comment | B25: 'Two drinks' is a fact. 'Alcohol had a significant negative impact' is a lecture.
A26: Effort first, then verdict | B26: Consistency is acknowledged before any result.
A27: Choice at the end of every sentence | B27: 'Your call', 'yours', 'worth it to you'. Never 'should'.
A28: A lapse is a data point, not a failure | B28: Off-plan nights are 'unknown' or 'different', never 'missed' or 'failed'.
A29: Verdicts on a fortnight, not a morning | B29: Daily feedback breeds score-chasing. Two-week verdicts breed knowledge.
A30: The scoreboard goes down | B30: Count and cost falling is the only progress shown.

Sheet Follow-up Questions
A1: The follow-up questions onboarding asks, and which rows fire each one
A2: Only rows that name a question get asked it. Most people see four to eight follow-ups in total, all chips, under a minute.
A4: Question type | B4: Wording the person sees | C4: How it's answered | D4: Rows that fire it | E4: Which rows
A5: dose & form | B5: Which form, and how much a day? | C5: Form chips specific to the item, plus a number box with the unit prefilled. The label on the bottle answers both; we say so. | D5: 26 | E5: Magnesium (any form), Magnesium L-threonate, Melatonin, L-theanine, Glycine, Ashwagandha (KSM-66 / Sensoril), Valerian, Tart cherry juice / extract, CBD, 5-HTP, Lavender oil, oral (Silexan), Sleep gummies (blend), Vitamin D3, Omega-3 fish oil, Krill oil, Creatine monohydrate, Beta-alanine, Collagen peptides, Hyaluronic acid (oral), Turmeric / curcumin, Glucosamine / chondroitin, Rhodiola, Saffron, Zinc (daily), Probiotic (generic daily), Berberine
A6: frequency | B6: How many times in the last 30 days? | C6: 0 · 1 to 3 · 4 to 7 · 8 or more. For memberships, the app can prefill this from calendar or check-in data where connected. | D6: 15 | E6: Electrolytes (LMNT etc.), Second (or third) coffee, Fluids after 8pm, Screens / phone in bed, Sauna / bathhouse membership, Cryotherapy sessions, Massage (monthly), Facials (monthly), Acupuncture, Chiropractor (maintenance visits), Personal trainer, Gym membership, Yoga / pilates studio, Float tank, Stretch studio (assisted stretching)
A7: clock time | B7: What time, usually? | C7: Before noon · 12 to 2pm · 2 to 5pm · after 5pm (item-specific variants below). For workouts this is read from the wearable and not asked. | D7: 11 | E7: Coffee after 2pm, Energy drinks, Matcha / green tea in the afternoon, Late dinner (within 2–3 h of bed), Nicotine pouches / vape, Training after 7pm, HIIT in the evening, Cold plunge / ice bath, Sauna (post-workout or evening), Afternoon nap (after 3pm or over 30 min), Bedroom temperature (thermostat)
A8: nights a week | B8: How many nights a week, usually? | C8: 0 · 1 to 2 · 3 to 4 · 5 or more. Asked plainly, no comment, no follow-up. | D8: 2 | E8: THC / cannabis for sleep, Alcohol in the evening
A9: last used | B9: When did you last use it? | C9: This week · this month · 1 to 3 months ago · longer · can't remember. 'Can't remember' is treated as 'longer'. | D9: 19 | E9: Meditation app (Calm, Headspace), Weighted blanket, Mouth tape, Nasal strips / dilator, Blue-light blocking glasses, Eye mask, Earplugs, White noise / sound machine, Sleep headphones / sleep stories, Sunrise alarm (Hatch etc.), Light therapy box (10,000 lux), Red light therapy panel, Massage gun, Compression boots (Normatec), Air purifier (bedroom), Humidifier, Vibration plate, LED face mask, Cold plunge / ice bath tub (owned)
A10: still paying | B10: Still paying for it? | C10: Yes · no · not sure. Prefilled from the subscriptions list where the person connected one. | D10: 3 | E10: Greens powder (AG1 etc.), Eight Sleep / cooling mattress pad, Continuous glucose monitor (no diabetes)
A11: overlap (automatic) | B11: (no question) | C11: Fires on its own when two or more items from the same overlap group are both in the inventory. The person is shown both and asked which one they'd keep. | D11: 39 | E11: Apigenin, Chamomile tea, Sleep tea blend (valerian, passionflower, lemon balm), Kava, Passionflower, Lemon balm, ZMA, Vitamin B12, B-complex, Multivitamin, Flaxseed oil (as omega-3), Pre-workout, Vitamin C (daily), Mushroom coffee, Vitamin K2, Bone broth, Morning sunlight (10 min outdoors), Second wearable (Oura plus WHOOP), Blood panel subscription (Function etc.), Premium gym membership (Equinox, Life Time), Boutique class membership (Barry's, SoulCycle, F45, Orangetheory), Second gym or studio membership, Class pack or studio credits, Fitness app subscription (Peloton app, Apple Fitness+, Ladder), Recovery studio membership (Restore, Remedy Place, Othership), Sauna or cold-plunge studio when you own one at home, Massage membership (Massage Envy, Squeeze), Second meditation or sleep app, Annual physical with bloodwork, Electrolytes plus sports drink, Collagen drinks and beauty gummies, Retinol or retinoid plus exfoliating acid on the same nights, Two exfoliants (scrub plus acid, or two acids), Toner (hydrating or balancing), Multiple hydrating serums (two hyaluronic acid products), Eye cream (when you already use a moisturiser), Facial plus at-home LED plus microcurrent (all three), Microcurrent device (NuFace), Gua sha / ice roller
A12: none | B12: (no question) | C12: Routes on the item name alone. | D12: 95 | E12: Magnesium spray / oil (transdermal), GABA (oral), Iron, Protein powder, BCAAs, Glutamine, Biotin, CoQ10, NMN / NR, Resveratrol, Lion's mane, Ginkgo biloba, Phosphatidylserine, Elderberry, Psyllium / fibre, Digestive enzymes, Apple cider vinegar, Green tea extract (EGCG), Fat burner / thermogenic, Testosterone booster (tribulus, fenugreek, D-AA), Tongkat ali, Maca, DHEA / pregnenolone, Taurine, Activated charcoal, Sea moss, Shilajit, Chlorophyll water, Colostrum, Nootropic stack (alpha-GPC etc.), Inositol, Calcium, Evening primrose oil, Decaf swap after noon, Big carbohydrate dinner, Dessert / sugar before bed, Fasting window / skipping breakfast, Kombucha / probiotic drinks, Morning workout before 8am, 10,000 steps / daily walk, Zone 2 cardio (3+ h/week), Strength training, Stretching / yoga before bed, Cold shower (morning), Hot bath / shower 1–2 h before bed, Breathwork (box, 4-7-8, physiological sigh), NSDR / yoga nidra, Journaling / worry list before bed, Gratitude practice, Reading (paper) before bed, Work email after 9pm, TV in the bedroom, Consistent wake time (±30 min), Weekend sleep-in (over 1 h), Snoozing the alarm, Checking the sleep score every morning, Grounding / earthing (sheets, mats), Salt lamp, Bedroom plants (for air), EMF blockers / anti-radiation stickers, Hydrogen / alkaline water, Jaw exerciser, Water filter, Smart lights (warm, dim in the evening), IV vitamin drips, Physical therapy, Therapy / counselling, Nutritionist / dietitian, Hyperbaric oxygen (wellness use), Lymphatic drainage massage, Colonic / detox cleanse, Consumer DNA wellness test, Hormone / peptide clinic (TRT, GLP-1, peptides), Sleep coach (CBT-I), Retreat / wellness weekend, Blackout / light leak, Phone charging in the bedroom, Pet in the bed, Partner's snoring or schedule, Kids waking you, Window open / fan at night, Mattress age (over 8 years), Pillow, Silk pillowcase, Candles / incense in the bedroom, Bedroom used for work, Separate bedrooms some nights, Meal delivery or meal-prep service, Nutrition or calorie app (premium), Hair growth gummies (biotin blends), Sunscreen (daily SPF 30+), Retinol / retinoid (nightly), Vitamin C serum, Unlisted device you haven't used in 30 days, Unlisted subscription you're still paying for
A14: Design rules for the questions
A15: Ask the question only when the answer can change the tier. A question whose answer changes nothing is a form field, and it gets cut.
A16: Chips, never typing, except the one number box for dose. Prefill from the label wording where possible ('the bottle says 400 mg: is that elemental or total?').
A17: Frequency and clock-time questions are prefilled from the wearable or a connected calendar wherever the data exists (workouts, naps, wake times, check-ins). Then the question becomes a confirmation, not a question.
A18: 'Nights a week' for alcohol and nicotine is asked once, plainly, with no comment on the answer and nothing that follows from it except the experiment design.
A19: The overlap check never asks a question. It shows both items side by side, with visits or last-used and the cost, and asks which one they'd keep. The person picks. The app never picks for them.

Sheet Overlap Groups
A1: Overlap groups: sets of items that do the same job
A2: Two or more from one group in the inventory fires the overlap check. Rule text is what the engine does; the person always chooses which to keep.
A4: Group | B4: Items in it | C4: Items | D4: What happens when two or more are present
A5: fitness memberships | B5: 7 | C5: Gym membership, Premium gym membership (Equinox, Life Time), Boutique class membership (Barry's, SoulCycle, F45, Orangetheory), Yoga / pilates studio, Second gym or studio membership, Class pack or studio credits, Fitness app subscription (Peloton app, Apple Fitness+, Ladder) | D5: Two or more → show both with visits per month and cost per visit; the one used less becomes Tier 2 (overlaps with something else). A fitness app alongside a gym they attend is fine; alongside a gym they don't attend, both are flagged.
A6: heat and cold | B6: 6 | C6: Sauna / bathhouse membership, Cryotherapy sessions, Recovery studio membership (Restore, Remedy Place, Othership), Sauna or cold-plunge studio when you own one at home, Cold plunge / ice bath tub (owned), Sauna (post-workout or evening) | D6: Owns a sauna or plunge AND pays for a studio that offers the same → the studio is Tier 2 (overlaps with something else). Two studios → the one used less.
A7: massage | B7: 4 | C7: Massage (monthly), Massage membership (Massage Envy, Squeeze), Massage gun, Compression boots (Normatec) | D7: Membership plus separate massages → the membership's banked credits are checked first. Massage gun plus boots plus membership → verdict shows all three and their total; nothing is auto-dropped, since each feels different.
A8: meditation apps | B8: 2 | C8: Meditation app (Calm, Headspace), Second meditation or sleep app | D8: Two → Tier 2 (overlaps with something else) for the one opened less in the last 30 days.
A9: wearables | B9: 1 | C9: Second wearable (Oura plus WHOOP) | D9: Two wearables → Tier 2 for the one they'd rather not wear.
A10: wake-up light | B10: 3 | C10: Sunrise alarm (Hatch etc.), Light therapy box (10,000 lux), Morning sunlight (10 min outdoors) | D10: A light box plus a sunrise alarm plus morning sunlight → the two devices overlap with the free one; shown, not auto-dropped.
A11: daily multivitamin | B11: 8 | C11: Multivitamin, Greens powder (AG1 etc.), Vitamin B12, Vitamin D3, Zinc (daily), Vitamin C (daily), Vitamin K2, B-complex | D11: Multivitamin or greens powder PLUS a separate B12, D, zinc, C or K2 → the separates are Tier 2 (overlaps with something else) unless doctor-sourced (Protected) or the multi's dose is under the studied amount for that one.
A12: omega-3 | B12: 3 | C12: Omega-3 fish oil, Krill oil, Flaxseed oil (as omega-3) | D12: Two or more → keep the fish oil, the others are Tier 2 (overlaps with something else).
A13: collagen | B13: 3 | C13: Collagen peptides, Bone broth, Collagen drinks and beauty gummies | D13: Collagen powder plus bone broth or collagen drinks → the second is Tier 2 (overlaps with something else). Powder wins on dose.
A14: caffeine before training | B14: 6 | C14: Pre-workout, Coffee after 2pm, Second (or third) coffee, Energy drinks, Mushroom coffee, Matcha / green tea in the afternoon | D14: Pre-workout AND coffee within an hour of each other → verdict shows the combined caffeine; pre-workout becomes Tier 2 (overlaps with something else) since the coffee is the same drug for less.
A15: sleep aids | B15: 15 | C15: Melatonin, Sleep gummies (blend), Sleep tea blend (valerian, passionflower, lemon balm), Valerian, Chamomile tea, Magnesium (any form), L-theanine, Glycine, Apigenin, 5-HTP, Passionflower, Lemon balm, CBD, Kava, Lavender oil, oral (Silexan) | D15: Three or more sleep aids → shown together with the total cost and the line 'you take {n} things for sleep and your sleep hasn't changed since {month}'. Melatonin plus sleep gummies → the gummies are Tier 2 (overlaps with something else).
A16: electrolytes | B16: 2 | C16: Electrolytes (LMNT etc.), Electrolytes plus sports drink | D16: Both → the sports drink is Tier 2 (overlaps with something else).
... A22: at-home skin devices | B22: 4 | C22: LED face mask, Microcurrent device (NuFace), Red light therapy panel, Gua sha / ice roller | D22: Two or more, each used less than weekly → Tier 2 (not being used) for the unused ones.

Sheet Worked Example
A1: Worked example: a premium-gym member's stack, routed on day one
A2: A made-up but typical inventory for the new target person. Answers are what they'd tap during onboarding. This is the day-one screen, before any experiment runs.
A4: Item | B4: Cost per month | C4: What they tapped | D4: Where it lands | E4: Back on day one | F4: Note
A5: Equinox membership | B5: 250 | C5: 11 visits last month | D5: Tier 3, keep | F5: Going. $23 a visit.
A6: Barry's membership | B6: 200 | C6: 2 visits last month; overlaps with Equinox | D6: Tier 2, overlaps with something else | E6: 200 | F6: Two memberships, one used. Keep Equinox.
A7: Restore recovery studio | B7: 250 | C7: 1 visit in 60 days | D7: Tier 2, not being used | E7: 250 | F7: $250 for one visit.
A8: Massage Envy membership | B8: 90 | C8: 3 credits banked, last visit July | D8: Tier 2, not being used | E8: 90 | F8: Use the credits, pause the billing.
A9: Calm subscription | B9: 15 | C9: last opened 2 months ago, still paying | D9: Tier 2, not being used | E9: 15 | F9: Resubscribe the week it's wanted.
A10: Peloton app | B10: 25 | C10: used 9 times last month | D10: Tier 3, keep | F10: Used.
A11: AG1 greens powder | B11: 90 | C11: still paying; no specific goal | D11: Tier 3, can't measure | F11: $1,080 a year shown. Their call.
A12: Magnesium citrate, 120 mg | B12: 22 | C12: form: citrate; dose: 120 mg elemental | D12: Tier 2, dose too low | E12: 22 | F12: Below 200 mg. Step up or drop.
A13: Collagen gummies | B13: 40 | C13: 2 g per serving | D13: Tier 2, dose too low | E13: 40 | F13: Trials used 10 g. Powder if they want it.
A14: Fish oil, 1 capsule | B14: 20 | C14: 300 mg EPA+DHA | D14: Tier 2, dose too low | E14: 20 | F14: Below 500 mg.
A15: Vitamin C serum, clear bottle | B15: 60 | C15: form unknown; serum has turned orange | D15: Tier 2, form not absorbed | E15: 60 | F15: Already oxidised.
A16: Toner | B16: 25 | C16: routine: cleanser, toner, serum, moisturiser | D16: Tier 2, overlaps with something else | E16: 25 | F16: The serum does this.
A17: Eye cream | B17: 45 | C17: same ingredient list as the moisturiser | D17: Tier 2, overlaps with something else | E17: 45 | F17: Same formula, smaller jar.
A18: Retinol, nightly | B18: 40 | D18: Tier 3, keep | F18: Strong evidence. Weekly skin rating.
A19: Sunscreen | B19: 20 | D19: Tier 3, keep | F19: Strongest evidence on the list.
A20: Monthly facial | B20: 150 | C20: went last month | D20: Tier 3, can't measure | F20: $1,800 a year shown; skin rating offered.
A21: Coffee, last cup around 4pm | B21: 0 | C21: clock time: 2 to 5pm | D21: Tier 1, tested on you | F21: First experiment. Expected effect 1.0.
A22: Drinks, 3 nights a week | B22: 80 | C22: nights a week: 3 to 4 | D22: Tier 1, observe only | F22: Second experiment. Expected effect 1.5.
A23: Training after 7pm | B23: 0 | C23: read from workouts: 4 evening sessions a week ending 9pm | D23: Tier 1, tested on you | F23: Third experiment; day-one hypothesis from 6 months of history.
A24: Dinner an hour before bed | B24: 0 | C24: clock time: under 1.5 h | D24: Tier 1, tested on you | F24: Fourth in the queue.
A25: Oura ring | B25: 6 | D25: Protected (it's the data source)
A27: Stack on arrival | B27: =COUNTA(A5:A25) -> 21 | C27: =SUM(B5:B25) -> 1428
A28: Dropped on day one, no experiment | B28: =COUNTIF(D5:D25,"Tier 2*") -> 10 | C28: =SUM(E5:E25) -> 767
A29: Lined up for testing | B29: =COUNTIF(D5:D25,"Tier 1*") -> 4
A30: Can't measure, cost shown | B30: =COUNTIF(D5:D25,"Tier 3, can*") -> 2
A31: Keep | B31: =COUNTIF(D5:D25,"Tier 3, keep") -> 4
A33: What this shows
A34: Ten items come off on day one and about $767 a month comes back, before a single experiment runs. Only three of the ten are supplements. Seven are services, apps and skincare, and those seven are $685 of the $767. That is the 'cut at least five things in 60 days' promise met on the first screen, for a person who owns two supplements.
A35: The day-one screen reads: 21 things, $1,342 a month. 10 come off today, $767 a month back. 4 lined up for testing. 3 we can't measure, here's what they cost. 4 to keep. That's the emotional peak of the flow, and it exists because of the follow-up questions and the overlap groups. Without them, this screen would show one drop.
A36: Every drop on this screen is one the person would agree with in a sentence: two gyms, one used. A studio visited once. Credits banked since July. An app still billing. A dose under the studied amount. A serum that's already gone orange. None of them is a judgement about the person.

Sheet Summary
A1: Summary (live formulas against the Items sheet; open in Excel to see the numbers)
A3: Natural tier | B3: Rows | C3: Share of rows | D3: Cost per month, added up
A4: 1 Tested on you | B4: =COUNTIF(Items!$S$2:$S$211,"1") -> 81 | C4: =IF($B$8=0,0,B4/$B$8) -> 0.38571429 | D4: =SUMIF(Items!$S$2:$S$211,"1",Items!$F$2:$F$211) -> 1391
A5: 2 No test needed | B5: =COUNTIF(Items!$S$2:$S$211,"2") -> 47 | C5: =IF($B$8=0,0,B5/$B$8) -> 0.22380952 | D5: =SUMIF(Items!$S$2:$S$211,"2",Items!$F$2:$F$211) -> 2200
A6: 3 Can't measure it | B6: =COUNTIF(Items!$S$2:$S$211,"3") -> 73 | C6: =IF($B$8=0,0,B6/$B$8) -> 0.34761905 | D6: =SUMIF(Items!$S$2:$S$211,"3",Items!$F$2:$F$211) -> 3964
A7: P Protected | B7: =COUNTIF(Items!$S$2:$S$211,"P") -> 9 | C7: =IF($B$8=0,0,B7/$B$8) -> 0.042857143 | D7: =SUMIF(Items!$S$2:$S$211,"P",Items!$F$2:$F$211) -> 1298
A8: Total | B8: =SUM(B4:B7) -> 210 | D8: =SUM(D4:D7) -> 8853
A10: Tier after the effect gate (what the engine uses) | B10: Rows
A11: 1 | B11: =COUNTIF(Items!$U$2:$U$211,"1") -> 16
A12: 1, queued (slow) | B12: =COUNTIF(Items!$U$2:$U$211,"1, queued (slow)") -> 3
A13: 1, queued (special design) | B13: =COUNTIF(Items!$U$2:$U$211,"1, queued (special design)") -> 1
A14: 3, effect too small | B14: =COUNTIF(Items!$U$2:$U$211,"3, effect too small") -> 61
A15: 2 | B15: =COUNTIF(Items!$U$2:$U$211,"2") -> 47
A16: 3 | B16: =COUNTIF(Items!$U$2:$U$211,"3") -> 73
A17: P | B17: =COUNTIF(Items!$U$2:$U$211,"P") -> 9
A19: By category | B19: Rows | C19: Natural Tier 1 | D19: Runnable Tier 1 after gate | E19: Tier 2 | F19: Tier 3 | G19: Protected
A20: supplement | B20: =COUNTIF(Items!$E$2:$E$211,"supplement") -> 76 | C20: =COUNTIFS(Items!$E$2:$E$211,"supplement",Items!$S$2:$S$211,"1") -> 19 | D20: =COUNTIFS(Items!$E$2:$E$211,"supplement",Items!$U$2:$U$211,"1") -> 2 | E20: =COUNTIFS(Items!$E$2:$E$211,"supplement",Items!$S$2:$S$211,"2") -> 22 | F20: =COUNTIFS(Items!$E$2:$E$211,"supplement",Items!$S$2:$S$211,"3") -> 32 | G20: =COUNTIFS(Items!$E$2:$E$211,"supplement",Items!$S$2:$S$211,"P") -> 3
A21: food/drink | B21: =COUNTIF(Items!$E$2:$E$211,"food/drink") -> 10 | C21: =COUNTIFS(Items!$E$2:$E$211,"food/drink",Items!$S$2:$S$211,"1") -> 5 | D21: =COUNTIFS(Items!$E$2:$E$211,"food/drink",Items!$U$2:$U$211,"1") -> 2 | E21: =COUNTIFS(Items!$E$2:$E$211,"food/drink",Items!$S$2:$S$211,"2") -> 2 | F21: =COUNTIFS(Items!$E$2:$E$211,"food/drink",Items!$S$2:$S$211,"3") -> 3 | G21: =COUNTIFS(Items!$E$2:$E$211,"food/drink",Items!$S$2:$S$211,"P") -> 0
A22: timing | B22: =COUNTIF(Items!$E$2:$E$211,"timing") -> 12 | C22: =COUNTIFS(Items!$E$2:$E$211,"timing",Items!$S$2:$S$211,"1") -> 12 | D22: =COUNTIFS(Items!$E$2:$E$211,"timing",Items!$U$2:$U$211,"1") -> 4 | E22: =COUNTIFS(Items!$E$2:$E$211,"timing",Items!$S$2:$S$211,"2") -> 0 | F22: =COUNTIFS(Items!$E$2:$E$211,"timing",Items!$S$2:$S$211,"3") -> 0 | G22: =COUNTIFS(Items!$E$2:$E$211,"timing",Items!$S$2:$S$211,"P") -> 0
A23: habit | B23: =COUNTIF(Items!$E$2:$E$211,"habit") -> 21 | C23: =COUNTIFS(Items!$E$2:$E$211,"habit",Items!$S$2:$S$211,"1") -> 18 | D23: =COUNTIFS(Items!$E$2:$E$211,"habit",Items!$U$2:$U$211,"1") -> 6 | E23: =COUNTIFS(Items!$E$2:$E$211,"habit",Items!$S$2:$S$211,"2") -> 0 | F23: =COUNTIFS(Items!$E$2:$E$211,"habit",Items!$S$2:$S$211,"3") -> 3 | G23: =COUNTIFS(Items!$E$2:$E$211,"habit",Items!$S$2:$S$211,"P") -> 0
A24: device | B24: =COUNTIF(Items!$E$2:$E$211,"device") -> 31 | C24: =COUNTIFS(Items!$E$2:$E$211,"device",Items!$S$2:$S$211,"1") -> 14 | D24: =COUNTIFS(Items!$E$2:$E$211,"device",Items!$U$2:$U$211,"1") -> 0 | E24: =COUNTIFS(Items!$E$2:$E$211,"device",Items!$S$2:$S$211,"2") -> 6 | F24: =COUNTIFS(Items!$E$2:$E$211,"device",Items!$S$2:$S$211,"3") -> 11 | G24: =COUNTIFS(Items!$E$2:$E$211,"device",Items!$S$2:$S$211,"P") -> 0
A25: service | B25: =COUNTIF(Items!$E$2:$E$211,"service") -> 37 | C25: =COUNTIFS(Items!$E$2:$E$211,"service",Items!$S$2:$S$211,"1") -> 4 | D25: =COUNTIFS(Items!$E$2:$E$211,"service",Items!$U$2:$U$211,"1") -> 1 | E25: =COUNTIFS(Items!$E$2:$E$211,"service",Items!$S$2:$S$211,"2") -> 10 | F25: =COUNTIFS(Items!$E$2:$E$211,"service",Items!$S$2:$S$211,"3") -> 17 | G25: =COUNTIFS(Items!$E$2:$E$211,"service",Items!$S$2:$S$211,"P") -> 6
A26: environment | B26: =COUNTIF(Items!$E$2:$E$211,"environment") -> 14 | C26: =COUNTIFS(Items!$E$2:$E$211,"environment",Items!$S$2:$S$211,"1") -> 9 | D26: =COUNTIFS(Items!$E$2:$E$211,"environment",Items!$U$2:$U$211,"1") -> 1 | E26: =COUNTIFS(Items!$E$2:$E$211,"environment",Items!$S$2:$S$211,"2") -> 1 | F26: =COUNTIFS(Items!$E$2:$E$211,"environment",Items!$S$2:$S$211,"3") -> 4 | G26: =COUNTIFS(Items!$E$2:$E$211,"environment",Items!$S$2:$S$211,"P") -> 0
A27: skincare | B27: =COUNTIF(Items!$E$2:$E$211,"skincare") -> 9 | C27: =COUNTIFS(Items!$E$2:$E$211,"skincare",Items!$S$2:$S$211,"1") -> 0 | D27: =COUNTIFS(Items!$E$2:$E$211,"skincare",Items!$U$2:$U$211,"1") -> 0 | E27: =COUNTIFS(Items!$E$2:$E$211,"skincare",Items!$S$2:$S$211,"2") -> 6 | F27: =COUNTIFS(Items!$E$2:$E$211,"skincare",Items!$S$2:$S$211,"3") -> 3 | G27: =COUNTIFS(Items!$E$2:$E$211,"skincare",Items!$S$2:$S$211,"P") -> 0
A29: Day-one drops, by reason | B29: Rows
A30: dose too low | B30: =COUNTIF(Items!$AB$2:$AB$211,"dose too low") -> 2
A31: form not absorbed | B31: =COUNTIF(Items!$AB$2:$AB$211,"form not absorbed") -> 1
A32: tested, found nothing | B32: =COUNTIF(Items!$AB$2:$AB$211,"tested, found nothing") -> 17
A33: no way it could work | B33: =COUNTIF(Items!$AB$2:$AB$211,"no way it could work") -> 13
A34: overlaps with something else | B34: =COUNTIF(Items!$AB$2:$AB$211,"overlaps with something else") -> 11
A35: not being used | B35: =COUNTIF(Items!$AB$2:$AB$211,"not being used") -> 3
A38: Evidence grade | B38: Rows
A39: A | B39: =COUNTIF(Items!$Y$2:$Y$211,"A") -> 27
A40: B | B40: =COUNTIF(Items!$Y$2:$Y$211,"B") -> 62
A41: C | B41: =COUNTIF(Items!$Y$2:$Y$211,"C") -> 77
A42: D | B42: =COUNTIF(Items!$Y$2:$Y$211,"D") -> 19
A43: N | B43: =COUNTIF(Items!$Y$2:$Y$211,"N") -> 25
A45: Rows needing a fact-check | B45: =COUNTIF(Items!$AK$2:$AK$211,"yes") -> 93
A46: Tier 2 rows needing a fact-check (should equal all Tier 2 rows) | B46: =COUNTIFS(Items!$S$2:$S$211,"2",Items!$AK$2:$AK$211,"yes") -> 47
A48: 'Share of rows' is the share of this catalogue, not of a typical person's stack. Real stacks are heavy on supplements, so a real person will have a higher Tier 3 share than the catalogue does.
